{"version":"0.4","title":"Home Page One","type":"page","content":[{"id":"1552eb92","settings":{"layout":"full_width","gap":"no","padding":{"unit":"px","top":"0","right":"30","bottom":"0","left":"30","isLinked":false},"padding_tablet":{"unit":"px","top":"0","right":"0","bottom":"0","left":"0","isLinked":false}},"elements":[{"id":"1ee55a1c","settings":{"_column_size":100},"elements":[{"id":"470794","settings":{"slider_cat":["home-one"]},"elements":[],"isInner":false,"widgetType":"htslider-slider-addons","elType":"widget"}],"isInner":false,"elType":"column"}],"isInner":false,"elType":"section"},{"id":"5ae48a23","settings":{"structure":"20","padding":{"unit":"px","top":"90","right":"0","bottom":"90","left":"0","isLinked":false}},"elements":[{"id":"5b86ac5c","settings":{"_column_size":50,"_inline_size":59.426},"elements":[{"id":"7f7c80be","settings":{"bannerimage":{"url":"http:\/\/demo.shrimpthemes.com\/1\/parlo\/wp-content\/uploads\/2019\/03\/banner_1.png","id":127},"bannerimagesize_size":"full","bannersubtitle":"35% off<br\/> Black Monday","bannertitle":"Lighting For<br\/>\nHome.","buttontxt":"Shop Now","buttonlink":{"url":"#","is_external":true,"nofollow":true},"_background_background":"classic","_background_color":"#fbf8eb","_background_color_stop":{"unit":"%","size":0,"sizes":[]},"_background_color_b_stop":{"unit":"%","size":100,"sizes":[]},"_background_gradient_angle":{"unit":"deg","size":180,"sizes":[]},"_background_xpos":{"unit":"px","size":0,"sizes":[]},"_background_xpos_tablet":{"unit":"px","size":0,"sizes":[]},"_background_xpos_mobile":{"unit":"px","size":0,"sizes":[]},"_background_ypos":{"unit":"px","size":0,"sizes":[]},"_background_ypos_tablet":{"unit":"px","size":0,"sizes":[]},"_background_ypos_mobile":{"unit":"px","size":0,"sizes":[]},"_background_bg_width":{"unit":"%","size":100,"sizes":[]},"_background_bg_width_tablet":{"unit":"px","size":"","sizes":[]},"_background_bg_width_mobile":{"unit":"px","size":"","sizes":[]},"_background_hover_color_stop":{"unit":"%","size":0,"sizes":[]},"_background_hover_color_b_stop":{"unit":"%","size":100,"sizes":[]},"_background_hover_gradient_angle":{"unit":"deg","size":180,"sizes":[]},"_background_hover_xpos":{"unit":"px","size":0,"sizes":[]},"_background_hover_xpos_tablet":{"unit":"px","size":0,"sizes":[]},"_background_hover_xpos_mobile":{"unit":"px","size":0,"sizes":[]},"_background_hover_ypos":{"unit":"px","size":0,"sizes":[]},"_background_hover_ypos_tablet":{"unit":"px","size":0,"sizes":[]},"_background_hover_ypos_mobile":{"unit":"px","size":0,"sizes":[]},"_background_hover_bg_width":{"unit":"%","size":100,"sizes":[]},"_background_hover_bg_width_tablet":{"unit":"px","size":"","sizes":[]},"_background_hover_bg_width_mobile":{"unit":"px","size":"","sizes":[]},"_background_hover_transition":{"unit":"px","size":"","sizes":[]},"_border_hover_transition":{"unit":"px","size":"","sizes":[]},"_element_custom_width":{"unit":"px","size":"","sizes":[]},"_element_custom_width_tablet":{"unit":"px","size":"","sizes":[]},"_element_custom_width_mobile":{"unit":"px","size":"","sizes":[]},"_offset_x":{"unit":"px","size":"0","sizes":[]},"_offset_x_tablet":{"unit":"px","size":"","sizes":[]},"_offset_x_mobile":{"unit":"px","size":"","sizes":[]},"_offset_x_end":{"unit":"px","size":"0","sizes":[]},"_offset_x_end_tablet":{"unit":"px","size":"","sizes":[]},"_offset_x_end_mobile":{"unit":"px","size":"","sizes":[]},"_offset_y":{"unit":"px","size":"0","sizes":[]},"_offset_y_tablet":{"unit":"px","size":"","sizes":[]},"_offset_y_mobile":{"unit":"px","size":"","sizes":[]},"_offset_y_end":{"unit":"px","size":"0","sizes":[]},"_offset_y_end_tablet":{"unit":"px","size":"","sizes":[]},"_offset_y_end_mobile":{"unit":"px","size":"","sizes":[]},"title_typography_typography":"custom","title_typography_font_family":"Poppins","title_typography_font_weight":"400","sub_title_typography_typography":"custom","sub_title_typography_font_family":"Poppins","sub_title_typography_font_weight":"500","title_typography_font_size_tablet":{"unit":"px","size":18,"sizes":[]}},"elements":[],"isInner":false,"widgetType":"woolentor-addbanner-addons","elType":"widget"}],"isInner":false,"elType":"column"},{"id":"67eb810","settings":{"_column_size":50,"_inline_size":40.574},"elements":[{"id":"283835f","settings":{"bannerimage":{"url":"http:\/\/demo.shrimpthemes.com\/1\/parlo\/wp-content\/uploads\/2019\/03\/banner_2.png","id":140},"bannerimagesize_size":"full","bannersubtitle":"15% off","bannertitle":"Table Shiner<br\/>\nMoving.","buttontxt":"Shop Now","buttonlink":{"url":"#","is_external":true,"nofollow":true},"_background_background":"classic","_background_color":"#fbf8eb","_background_color_stop":{"unit":"%","size":0,"sizes":[]},"_background_color_b_stop":{"unit":"%","size":100,"sizes":[]},"_background_gradient_angle":{"unit":"deg","size":180,"sizes":[]},"_background_xpos":{"unit":"px","size":0,"sizes":[]},"_background_xpos_tablet":{"unit":"px","size":0,"sizes":[]},"_background_xpos_mobile":{"unit":"px","size":0,"sizes":[]},"_background_ypos":{"unit":"px","size":0,"sizes":[]},"_background_ypos_tablet":{"unit":"px","size":0,"sizes":[]},"_background_ypos_mobile":{"unit":"px","size":0,"sizes":[]},"_background_bg_width":{"unit":"%","size":100,"sizes":[]},"_background_bg_width_tablet":{"unit":"px","size":"","sizes":[]},"_background_bg_width_mobile":{"unit":"px","size":"","sizes":[]},"_background_hover_color_stop":{"unit":"%","size":0,"sizes":[]},"_background_hover_color_b_stop":{"unit":"%","size":100,"sizes":[]},"_background_hover_gradient_angle":{"unit":"deg","size":180,"sizes":[]},"_background_hover_xpos":{"unit":"px","size":0,"sizes":[]},"_background_hover_xpos_tablet":{"unit":"px","size":0,"sizes":[]},"_background_hover_xpos_mobile":{"unit":"px","size":0,"sizes":[]},"_background_hover_ypos":{"unit":"px","size":0,"sizes":[]},"_background_hover_ypos_tablet":{"unit":"px","size":0,"sizes":[]},"_background_hover_ypos_mobile":{"unit":"px","size":0,"sizes":[]},"_background_hover_bg_width":{"unit":"%","size":100,"sizes":[]},"_background_hover_bg_width_tablet":{"unit":"px","size":"","sizes":[]},"_background_hover_bg_width_mobile":{"unit":"px","size":"","sizes":[]},"_background_hover_transition":{"unit":"px","size":"","sizes":[]},"_border_hover_transition":{"unit":"px","size":"","sizes":[]},"_element_custom_width":{"unit":"px","size":"","sizes":[]},"_element_custom_width_tablet":{"unit":"px","size":"","sizes":[]},"_element_custom_width_mobile":{"unit":"px","size":"","sizes":[]},"_offset_x":{"unit":"px","size":"0","sizes":[]},"_offset_x_tablet":{"unit":"px","size":"","sizes":[]},"_offset_x_mobile":{"unit":"px","size":"","sizes":[]},"_offset_x_end":{"unit":"px","size":"0","sizes":[]},"_offset_x_end_tablet":{"unit":"px","size":"","sizes":[]},"_offset_x_end_mobile":{"unit":"px","size":"","sizes":[]},"_offset_y":{"unit":"px","size":"0","sizes":[]},"_offset_y_tablet":{"unit":"px","size":"","sizes":[]},"_offset_y_mobile":{"unit":"px","size":"","sizes":[]},"_offset_y_end":{"unit":"px","size":"0","sizes":[]},"_offset_y_end_tablet":{"unit":"px","size":"","sizes":[]},"_offset_y_end_mobile":{"unit":"px","size":"","sizes":[]},"title_typography_typography":"custom","title_typography_font_family":"Poppins","title_typography_font_weight":"400","sub_title_typography_typography":"custom","sub_title_typography_font_family":"Poppins","sub_title_typography_font_weight":"500","content_alignment":"right","title_typography_font_size":{"unit":"px","size":"","sizes":[]},"title_typography_font_size_tablet":{"unit":"px","size":18,"sizes":[]},"title_typography_font_size_mobile":{"unit":"px","size":"","sizes":[]},"title_typography_line_height":{"unit":"em","size":"","sizes":[]},"title_typography_line_height_tablet":{"unit":"em","size":"","sizes":[]},"title_typography_line_height_mobile":{"unit":"em","size":"","sizes":[]},"title_typography_letter_spacing":{"unit":"px","size":"","sizes":[]},"title_typography_letter_spacing_tablet":{"unit":"px","size":"","sizes":[]},"title_typography_letter_spacing_mobile":{"unit":"px","size":"","sizes":[]},"sub_title_typography_font_size":{"unit":"px","size":"","sizes":[]},"sub_title_typography_font_size_tablet":{"unit":"px","size":"","sizes":[]},"sub_title_typography_font_size_mobile":{"unit":"px","size":"","sizes":[]},"sub_title_typography_line_height":{"unit":"em","size":"","sizes":[]},"sub_title_typography_line_height_tablet":{"unit":"em","size":"","sizes":[]},"sub_title_typography_line_height_mobile":{"unit":"em","size":"","sizes":[]},"sub_title_typography_letter_spacing":{"unit":"px","size":"","sizes":[]},"sub_title_typography_letter_spacing_tablet":{"unit":"px","size":"","sizes":[]},"sub_title_typography_letter_spacing_mobile":{"unit":"px","size":"","sizes":[]},"button_typography_font_size":{"unit":"px","size":"","sizes":[]},"button_typography_font_size_tablet":{"unit":"px","size":"","sizes":[]},"button_typography_font_size_mobile":{"unit":"px","size":"","sizes":[]},"button_typography_line_height":{"unit":"em","size":"","sizes":[]},"button_typography_line_height_tablet":{"unit":"em","size":"","sizes":[]},"button_typography_line_height_mobile":{"unit":"em","size":"","sizes":[]},"button_typography_letter_spacing":{"unit":"px","size":"","sizes":[]},"button_typography_letter_spacing_tablet":{"unit":"px","size":"","sizes":[]},"button_typography_letter_spacing_mobile":{"unit":"px","size":"","sizes":[]},"_padding_tablet":{"unit":"px","top":"15","right":"0","bottom":"15","left":"0","isLinked":false}},"elements":[],"isInner":false,"widgetType":"woolentor-addbanner-addons","elType":"widget"},{"id":"3070e425","settings":{"bannerimage":{"url":"http:\/\/demo.shrimpthemes.com\/1\/parlo\/wp-content\/uploads\/2019\/03\/banner_3.png","id":143},"bannerimagesize_size":"full","bannersubtitle":"Black Friday","bannertitle":"Wall Lighting<br\/>\nBlack.","buttontxt":"Shop Now","buttonlink":{"url":"#","is_external":true,"nofollow":true},"_background_background":"classic","_background_color":"#effafa","_background_color_stop":{"unit":"%","size":0,"sizes":[]},"_background_color_b_stop":{"unit":"%","size":100,"sizes":[]},"_background_gradient_angle":{"unit":"deg","size":180,"sizes":[]},"_background_xpos":{"unit":"px","size":0,"sizes":[]},"_background_xpos_tablet":{"unit":"px","size":0,"sizes":[]},"_background_xpos_mobile":{"unit":"px","size":0,"sizes":[]},"_background_ypos":{"unit":"px","size":0,"sizes":[]},"_background_ypos_tablet":{"unit":"px","size":0,"sizes":[]},"_background_ypos_mobile":{"unit":"px","size":0,"sizes":[]},"_background_bg_width":{"unit":"%","size":100,"sizes":[]},"_background_bg_width_tablet":{"unit":"px","size":"","sizes":[]},"_background_bg_width_mobile":{"unit":"px","size":"","sizes":[]},"_background_hover_color_stop":{"unit":"%","size":0,"sizes":[]},"_background_hover_color_b_stop":{"unit":"%","size":100,"sizes":[]},"_background_hover_gradient_angle":{"unit":"deg","size":180,"sizes":[]},"_background_hover_xpos":{"unit":"px","size":0,"sizes":[]},"_background_hover_xpos_tablet":{"unit":"px","size":0,"sizes":[]},"_background_hover_xpos_mobile":{"unit":"px","size":0,"sizes":[]},"_background_hover_ypos":{"unit":"px","size":0,"sizes":[]},"_background_hover_ypos_tablet":{"unit":"px","size":0,"sizes":[]},"_background_hover_ypos_mobile":{"unit":"px","size":0,"sizes":[]},"_background_hover_bg_width":{"unit":"%","size":100,"sizes":[]},"_background_hover_bg_width_tablet":{"unit":"px","size":"","sizes":[]},"_background_hover_bg_width_mobile":{"unit":"px","size":"","sizes":[]},"_background_hover_transition":{"unit":"px","size":"","sizes":[]},"_border_hover_transition":{"unit":"px","size":"","sizes":[]},"_element_custom_width":{"unit":"px","size":"","sizes":[]},"_element_custom_width_tablet":{"unit":"px","size":"","sizes":[]},"_element_custom_width_mobile":{"unit":"px","size":"","sizes":[]},"_offset_x":{"unit":"px","size":"0","sizes":[]},"_offset_x_tablet":{"unit":"px","size":"","sizes":[]},"_offset_x_mobile":{"unit":"px","size":"","sizes":[]},"_offset_x_end":{"unit":"px","size":"0","sizes":[]},"_offset_x_end_tablet":{"unit":"px","size":"","sizes":[]},"_offset_x_end_mobile":{"unit":"px","size":"","sizes":[]},"_offset_y":{"unit":"px","size":"0","sizes":[]},"_offset_y_tablet":{"unit":"px","size":"","sizes":[]},"_offset_y_mobile":{"unit":"px","size":"","sizes":[]},"_offset_y_end":{"unit":"px","size":"0","sizes":[]},"_offset_y_end_tablet":{"unit":"px","size":"","sizes":[]},"_offset_y_end_mobile":{"unit":"px","size":"","sizes":[]},"title_typography_typography":"custom","title_typography_font_family":"Poppins","title_typography_font_weight":"400","sub_title_typography_typography":"custom","sub_title_typography_font_family":"Poppins","sub_title_typography_font_weight":"500","content_alignment":"right","title_typography_font_size":{"unit":"px","size":"","sizes":[]},"title_typography_font_size_tablet":{"unit":"px","size":16,"sizes":[]},"title_typography_font_size_mobile":{"unit":"px","size":"","sizes":[]},"title_typography_line_height":{"unit":"em","size":"","sizes":[]},"title_typography_line_height_tablet":{"unit":"em","size":"","sizes":[]},"title_typography_line_height_mobile":{"unit":"em","size":"","sizes":[]},"title_typography_letter_spacing":{"unit":"px","size":"","sizes":[]},"title_typography_letter_spacing_tablet":{"unit":"px","size":"","sizes":[]},"title_typography_letter_spacing_mobile":{"unit":"px","size":"","sizes":[]},"sub_title_typography_font_size":{"unit":"px","size":"","sizes":[]},"sub_title_typography_font_size_tablet":{"unit":"px","size":"","sizes":[]},"sub_title_typography_font_size_mobile":{"unit":"px","size":"","sizes":[]},"sub_title_typography_line_height":{"unit":"em","size":"","sizes":[]},"sub_title_typography_line_height_tablet":{"unit":"em","size":"","sizes":[]},"sub_title_typography_line_height_mobile":{"unit":"em","size":"","sizes":[]},"sub_title_typography_letter_spacing":{"unit":"px","size":"","sizes":[]},"sub_title_typography_letter_spacing_tablet":{"unit":"px","size":"","sizes":[]},"sub_title_typography_letter_spacing_mobile":{"unit":"px","size":"","sizes":[]},"button_typography_font_size":{"unit":"px","size":"","sizes":[]},"button_typography_font_size_tablet":{"unit":"px","size":"","sizes":[]},"button_typography_font_size_mobile":{"unit":"px","size":"","sizes":[]},"button_typography_line_height":{"unit":"em","size":"","sizes":[]},"button_typography_line_height_tablet":{"unit":"em","size":"","sizes":[]},"button_typography_line_height_mobile":{"unit":"em","size":"","sizes":[]},"button_typography_letter_spacing":{"unit":"px","size":"","sizes":[]},"button_typography_letter_spacing_tablet":{"unit":"px","size":"","sizes":[]},"button_typography_letter_spacing_mobile":{"unit":"px","size":"","sizes":[]},"_padding":{"unit":"px","top":"20","right":"0","bottom":"20","left":"0","isLinked":false},"_margin_tablet":{"unit":"px","top":"30","right":"0","bottom":"0","left":"0","isLinked":false},"_padding_tablet":{"unit":"px","top":"20","right":"0","bottom":"20","left":"0","isLinked":false}},"elements":[],"isInner":false,"widgetType":"woolentor-addbanner-addons","elType":"widget"}],"isInner":false,"elType":"column"}],"isInner":false,"elType":"section"},{"id":"29c6b918","settings":[],"elements":[{"id":"5c12bf6","settings":{"_column_size":100},"elements":[{"id":"434b37cc","settings":{"title":"All Products","align":"center","typography_typography":"custom","typography_font_family":"Poppins","typography_font_size":{"unit":"px","size":30,"sizes":[]},"typography_font_weight":"500"},"elements":[],"isInner":false,"widgetType":"heading","elType":"widget"},{"id":"7b01244c","settings":{"title":"Contrary to popular belief, Lorem Ipsum is not simply random <br\/>text. It has roots in a piece of classical","header_size":"p","align":"center","title_color":"#5a5a5a","typography_typography":"custom","typography_font_family":"Poppins","typography_font_weight":"400","typography_line_height":{"unit":"px","size":24,"sizes":[]}},"elements":[],"isInner":false,"widgetType":"heading","elType":"widget"},{"id":"410145e","settings":{"product_layout_style":"tab","woolentor_product_grid_column":"4","woolentor_product_grid_products_count":4,"woolentor_product_grid_categories":["accessories","decor","hoodies"],"product_content_style":"2","action_button_show_on":"hover","product_category_typography_typography":"custom","product_category_typography_font_family":"Poppins","product_category_typography_font_weight":"400","product_title_typography_typography":"custom","product_title_typography_font_family":"Poppins","product_title_typography_font_size":{"unit":"px","size":"","sizes":[]},"product_title_typography_font_weight":"400","product_sale_price_color":"#ff3535","product_sale_price_typography_typography":"custom","product_sale_price_typography_font_family":"Poppins","product_sale_price_typography_font_size":{"unit":"px","size":16,"sizes":[]},"product_sale_price_typography_font_weight":"600","product_regular_price_color":"#4a4a4a","product_regular_price_typography_typography":"custom","product_regular_price_typography_font_family":"Poppins","product_regular_price_typography_font_size":{"unit":"px","size":13,"sizes":[]},"product_regular_price_typography_font_weight":"400","tabmenutypography_typography":"custom","tabmenutypography_font_family":"Poppins","tabmenutypography_font_size":{"unit":"px","size":14,"sizes":[]},"tabmenutypography_font_weight":"400","tab_menu_color":"#1f2226","product_tab_menu_bg_color":"#f1f1f1","tabmenu_border_radius":{"unit":"px","top":"0","right":"0","bottom":"0","left":"0","isLinked":false},"tab_menu_hover_color":"#ffffff","product_tab_menu_hover_bg_color":"#1f2226","tabmenu_hover_border_border":"solid","tabmenu_hover_border_width":{"unit":"px","top":"0","right":"0","bottom":"0","left":"0","isLinked":true},"tabmenu_border_border":"solid","tabmenu_border_width":{"unit":"px","top":"0","right":"0","bottom":"0","left":"0","isLinked":true}},"elements":[],"isInner":false,"widgetType":"woolentor-universal-product","elType":"widget"}],"isInner":false,"elType":"column"}],"isInner":false,"elType":"section"},{"id":"1ad04245","settings":{"background_background":"classic","background_image":{"url":"http:\/\/demo.shrimpthemes.com\/1\/parlo\/wp-content\/uploads\/2019\/03\/testimonial_bg.png","id":166},"background_position":"center center","background_repeat":"no-repeat","background_size":"cover","margin":{"unit":"px","top":"60","right":0,"bottom":"100","left":0,"isLinked":false},"padding":{"unit":"px","top":"100","right":"0","bottom":"100","left":"0","isLinked":false},"structure":"30"},"elements":[{"id":"6c54c4ce","settings":{"_column_size":33,"_inline_size":15,"background_color_stop":{"unit":"%","size":0,"sizes":[]},"background_color_b_stop":{"unit":"%","size":100,"sizes":[]},"background_gradient_angle":{"unit":"deg","size":180,"sizes":[]},"background_xpos":{"unit":"px","size":0,"sizes":[]},"background_xpos_tablet":{"unit":"px","size":0,"sizes":[]},"background_xpos_mobile":{"unit":"px","size":0,"sizes":[]},"background_ypos":{"unit":"px","size":0,"sizes":[]},"background_ypos_tablet":{"unit":"px","size":0,"sizes":[]},"background_ypos_mobile":{"unit":"px","size":0,"sizes":[]},"background_bg_width":{"unit":"%","size":100,"sizes":[]},"background_bg_width_tablet":{"unit":"px","size":"","sizes":[]},"background_bg_width_mobile":{"unit":"px","size":"","sizes":[]},"background_hover_color_stop":{"unit":"%","size":0,"sizes":[]},"background_hover_color_b_stop":{"unit":"%","size":100,"sizes":[]},"background_hover_gradient_angle":{"unit":"deg","size":180,"sizes":[]},"background_hover_xpos":{"unit":"px","size":0,"sizes":[]},"background_hover_xpos_tablet":{"unit":"px","size":0,"sizes":[]},"background_hover_xpos_mobile":{"unit":"px","size":0,"sizes":[]},"background_hover_ypos":{"unit":"px","size":0,"sizes":[]},"background_hover_ypos_tablet":{"unit":"px","size":0,"sizes":[]},"background_hover_ypos_mobile":{"unit":"px","size":0,"sizes":[]},"background_hover_bg_width":{"unit":"%","size":100,"sizes":[]},"background_hover_bg_width_tablet":{"unit":"px","size":"","sizes":[]},"background_hover_bg_width_mobile":{"unit":"px","size":"","sizes":[]},"background_hover_transition":{"unit":"px","size":0.3,"sizes":[]},"background_overlay_color_stop":{"unit":"%","size":0,"sizes":[]},"background_overlay_color_b_stop":{"unit":"%","size":100,"sizes":[]},"background_overlay_gradient_angle":{"unit":"deg","size":180,"sizes":[]},"background_overlay_xpos":{"unit":"px","size":0,"sizes":[]},"background_overlay_xpos_tablet":{"unit":"px","size":0,"sizes":[]},"background_overlay_xpos_mobile":{"unit":"px","size":0,"sizes":[]},"background_overlay_ypos":{"unit":"px","size":0,"sizes":[]},"background_overlay_ypos_tablet":{"unit":"px","size":0,"sizes":[]},"background_overlay_ypos_mobile":{"unit":"px","size":0,"sizes":[]},"background_overlay_bg_width":{"unit":"%","size":100,"sizes":[]},"background_overlay_bg_width_tablet":{"unit":"px","size":"","sizes":[]},"background_overlay_bg_width_mobile":{"unit":"px","size":"","sizes":[]},"background_overlay_opacity":{"unit":"px","size":0.5,"sizes":[]},"css_filters_blur":{"unit":"px","size":0,"sizes":[]},"css_filters_brightness":{"unit":"px","size":100,"sizes":[]},"css_filters_contrast":{"unit":"px","size":100,"sizes":[]},"css_filters_saturate":{"unit":"px","size":100,"sizes":[]},"css_filters_hue":{"unit":"px","size":0,"sizes":[]},"background_overlay_hover_color_stop":{"unit":"%","size":0,"sizes":[]},"background_overlay_hover_color_b_stop":{"unit":"%","size":100,"sizes":[]},"background_overlay_hover_gradient_angle":{"unit":"deg","size":180,"sizes":[]},"background_overlay_hover_xpos":{"unit":"px","size":0,"sizes":[]},"background_overlay_hover_xpos_tablet":{"unit":"px","size":0,"sizes":[]},"background_overlay_hover_xpos_mobile":{"unit":"px","size":0,"sizes":[]},"background_overlay_hover_ypos":{"unit":"px","size":0,"sizes":[]},"background_overlay_hover_ypos_tablet":{"unit":"px","size":0,"sizes":[]},"background_overlay_hover_ypos_mobile":{"unit":"px","size":0,"sizes":[]},"background_overlay_hover_bg_width":{"unit":"%","size":100,"sizes":[]},"background_overlay_hover_bg_width_tablet":{"unit":"px","size":"","sizes":[]},"background_overlay_hover_bg_width_mobile":{"unit":"px","size":"","sizes":[]},"background_overlay_hover_opacity":{"unit":"px","size":0.5,"sizes":[]},"css_filters_hover_blur":{"unit":"px","size":0,"sizes":[]},"css_filters_hover_brightness":{"unit":"px","size":100,"sizes":[]},"css_filters_hover_contrast":{"unit":"px","size":100,"sizes":[]},"css_filters_hover_saturate":{"unit":"px","size":100,"sizes":[]},"css_filters_hover_hue":{"unit":"px","size":0,"sizes":[]},"background_overlay_hover_transition":{"unit":"px","size":0.3,"sizes":[]},"border_hover_transition":{"unit":"px","size":0.3,"sizes":[]}},"elements":[],"isInner":false,"elType":"column"},{"id":"7468d484","settings":{"_column_size":33,"_inline_size":69.332},"elements":[{"id":"9dabfec","settings":{"testimonial_list":[{"client_name":"Carolina Monntoya","client_say":"Lorem ipsum dolor sit amet consectetur adipisicing elit sed do eiusmod tempor incididunt ut labore et dolore Lorem ipsum dolor sit amet, consectetur adipisicing elit, sed do eiusmod tempor incididunt ut labore et dolore magna aliqua.","_id":"fd2fe97","client_image":{"url":"http:\/\/demo.shrimpthemes.com\/1\/parlo\/wp-content\/uploads\/2019\/03\/testimonial_thumb.png","id":188},"client_imagesize_size":"large","client_imagesize_custom_dimension":{"width":"","height":""}},{"client_name":"Peter Rose","client_say":"Lorem ipsum dolor sit amet consectetur adipisicing elit sed do eiusmod tempor incididunt ut labore et dolore Lorem ipsum dolor sit amet, consectetur adipisicing elit, sed do eiusmod tempor incididunt ut labore et dolore magna aliqua.","_id":"4611f1a","client_image":{"url":"http:\/\/demo.shrimpthemes.com\/1\/parlo\/wp-content\/uploads\/2019\/03\/testimonial_thumb.png","id":188},"client_imagesize_size":"large","client_imagesize_custom_dimension":{"width":"","height":""}},{"client_name":"Gerald Gilbert","client_say":"Lorem ipsum dolor sit amet consectetur adipisicing elit sed do eiusmod tempor incididunt ut labore et dolore Lorem ipsum dolor sit amet, consectetur adipisicing elit, sed do eiusmod tempor incididunt ut labore et dolore magna aliqua.","_id":"0015fbb","client_image":{"url":"http:\/\/demo.shrimpthemes.com\/1\/parlo\/wp-content\/uploads\/2019\/03\/testimonial_thumb.png","id":188},"client_imagesize_size":"large","client_imagesize_custom_dimension":{"width":"","height":""}}],"client_image_divider":{"url":"http:\/\/demo.shrimpthemes.com\/1\/parlo\/wp-content\/uploads\/2019\/03\/testimonial_qute.png","id":189},"slarrows":"","testimonial_name_typography_typography":"custom","testimonial_name_typography_font_family":"Poppins","testimonial_name_typography_font_size":{"unit":"px","size":"","sizes":[]},"testimonial_name_typography_font_weight":"600","testimonial_clsay_typography_typography":"custom","testimonial_clsay_typography_font_family":"Poppins","testimonial_clsay_typography_font_weight":"400"},"elements":[],"isInner":false,"widgetType":"parlo-testimonial-addons","elType":"widget"}],"isInner":false,"elType":"column"},{"id":"9f15311","settings":{"_column_size":33,"_inline_size":15},"elements":[],"isInner":false,"elType":"column"}],"isInner":false,"elType":"section"},{"id":"7d8cc4f","settings":{"content_width":{"unit":"px","size":"","sizes":[]},"custom_height":{"unit":"px","size":400,"sizes":[]},"custom_height_tablet":{"unit":"px","size":"","sizes":[]},"custom_height_mobile":{"unit":"px","size":"","sizes":[]},"background_color_stop":{"unit":"%","size":0,"sizes":[]},"background_color_b_stop":{"unit":"%","size":100,"sizes":[]},"background_gradient_angle":{"unit":"deg","size":180,"sizes":[]},"background_xpos":{"unit":"px","size":0,"sizes":[]},"background_xpos_tablet":{"unit":"px","size":0,"sizes":[]},"background_xpos_mobile":{"unit":"px","size":0,"sizes":[]},"background_ypos":{"unit":"px","size":0,"sizes":[]},"background_ypos_tablet":{"unit":"px","size":0,"sizes":[]},"background_ypos_mobile":{"unit":"px","size":0,"sizes":[]},"background_bg_width":{"unit":"%","size":100,"sizes":[]},"background_bg_width_tablet":{"unit":"px","size":"","sizes":[]},"background_bg_width_mobile":{"unit":"px","size":"","sizes":[]},"background_hover_color_stop":{"unit":"%","size":0,"sizes":[]},"background_hover_color_b_stop":{"unit":"%","size":100,"sizes":[]},"background_hover_gradient_angle":{"unit":"deg","size":180,"sizes":[]},"background_hover_xpos":{"unit":"px","size":0,"sizes":[]},"background_hover_xpos_tablet":{"unit":"px","size":0,"sizes":[]},"background_hover_xpos_mobile":{"unit":"px","size":0,"sizes":[]},"background_hover_ypos":{"unit":"px","size":0,"sizes":[]},"background_hover_ypos_tablet":{"unit":"px","size":0,"sizes":[]},"background_hover_ypos_mobile":{"unit":"px","size":0,"sizes":[]},"background_hover_bg_width":{"unit":"%","size":100,"sizes":[]},"background_hover_bg_width_tablet":{"unit":"px","size":"","sizes":[]},"background_hover_bg_width_mobile":{"unit":"px","size":"","sizes":[]},"background_hover_transition":{"unit":"px","size":0.3,"sizes":[]},"background_overlay_color_stop":{"unit":"%","size":0,"sizes":[]},"background_overlay_color_b_stop":{"unit":"%","size":100,"sizes":[]},"background_overlay_gradient_angle":{"unit":"deg","size":180,"sizes":[]},"background_overlay_xpos":{"unit":"px","size":0,"sizes":[]},"background_overlay_xpos_tablet":{"unit":"px","size":0,"sizes":[]},"background_overlay_xpos_mobile":{"unit":"px","size":0,"sizes":[]},"background_overlay_ypos":{"unit":"px","size":0,"sizes":[]},"background_overlay_ypos_tablet":{"unit":"px","size":0,"sizes":[]},"background_overlay_ypos_mobile":{"unit":"px","size":0,"sizes":[]},"background_overlay_bg_width":{"unit":"%","size":100,"sizes":[]},"background_overlay_bg_width_tablet":{"unit":"px","size":"","sizes":[]},"background_overlay_bg_width_mobile":{"unit":"px","size":"","sizes":[]},"background_overlay_opacity":{"unit":"px","size":0.5,"sizes":[]},"css_filters_blur":{"unit":"px","size":0,"sizes":[]},"css_filters_brightness":{"unit":"px","size":100,"sizes":[]},"css_filters_contrast":{"unit":"px","size":100,"sizes":[]},"css_filters_saturate":{"unit":"px","size":100,"sizes":[]},"css_filters_hue":{"unit":"px","size":0,"sizes":[]},"background_overlay_hover_color_stop":{"unit":"%","size":0,"sizes":[]},"background_overlay_hover_color_b_stop":{"unit":"%","size":100,"sizes":[]},"background_overlay_hover_gradient_angle":{"unit":"deg","size":180,"sizes":[]},"background_overlay_hover_xpos":{"unit":"px","size":0,"sizes":[]},"background_overlay_hover_xpos_tablet":{"unit":"px","size":0,"sizes":[]},"background_overlay_hover_xpos_mobile":{"unit":"px","size":0,"sizes":[]},"background_overlay_hover_ypos":{"unit":"px","size":0,"sizes":[]},"background_overlay_hover_ypos_tablet":{"unit":"px","size":0,"sizes":[]},"background_overlay_hover_ypos_mobile":{"unit":"px","size":0,"sizes":[]},"background_overlay_hover_bg_width":{"unit":"%","size":100,"sizes":[]},"background_overlay_hover_bg_width_tablet":{"unit":"px","size":"","sizes":[]},"background_overlay_hover_bg_width_mobile":{"unit":"px","size":"","sizes":[]},"background_overlay_hover_opacity":{"unit":"px","size":0.5,"sizes":[]},"css_filters_hover_blur":{"unit":"px","size":0,"sizes":[]},"css_filters_hover_brightness":{"unit":"px","size":100,"sizes":[]},"css_filters_hover_contrast":{"unit":"px","size":100,"sizes":[]},"css_filters_hover_saturate":{"unit":"px","size":100,"sizes":[]},"css_filters_hover_hue":{"unit":"px","size":0,"sizes":[]},"background_overlay_hover_transition":{"unit":"px","size":0.3,"sizes":[]},"border_hover_transition":{"unit":"px","size":0.3,"sizes":[]},"shape_divider_top_width":{"unit":"%","size":"","sizes":[]},"shape_divider_top_width_tablet":{"unit":"%","size":"","sizes":[]},"shape_divider_top_width_mobile":{"unit":"%","size":"","sizes":[]},"shape_divider_top_height":{"unit":"px","size":"","sizes":[]},"shape_divider_top_height_tablet":{"unit":"px","size":"","sizes":[]},"shape_divider_top_height_mobile":{"unit":"px","size":"","sizes":[]},"shape_divider_bottom_width":{"unit":"%","size":"","sizes":[]},"shape_divider_bottom_width_tablet":{"unit":"%","size":"","sizes":[]},"shape_divider_bottom_width_mobile":{"unit":"%","size":"","sizes":[]},"shape_divider_bottom_height":{"unit":"px","size":"","sizes":[]},"shape_divider_bottom_height_tablet":{"unit":"px","size":"","sizes":[]},"shape_divider_bottom_height_mobile":{"unit":"px","size":"","sizes":[]}},"elements":[{"id":"765c2c71","settings":{"_column_size":100,"background_color_stop":{"unit":"%","size":0,"sizes":[]},"background_color_b_stop":{"unit":"%","size":100,"sizes":[]},"background_gradient_angle":{"unit":"deg","size":180,"sizes":[]},"background_xpos":{"unit":"px","size":0,"sizes":[]},"background_xpos_tablet":{"unit":"px","size":0,"sizes":[]},"background_xpos_mobile":{"unit":"px","size":0,"sizes":[]},"background_ypos":{"unit":"px","size":0,"sizes":[]},"background_ypos_tablet":{"unit":"px","size":0,"sizes":[]},"background_ypos_mobile":{"unit":"px","size":0,"sizes":[]},"background_bg_width":{"unit":"%","size":100,"sizes":[]},"background_bg_width_tablet":{"unit":"px","size":"","sizes":[]},"background_bg_width_mobile":{"unit":"px","size":"","sizes":[]},"background_hover_color_stop":{"unit":"%","size":0,"sizes":[]},"background_hover_color_b_stop":{"unit":"%","size":100,"sizes":[]},"background_hover_gradient_angle":{"unit":"deg","size":180,"sizes":[]},"background_hover_xpos":{"unit":"px","size":0,"sizes":[]},"background_hover_xpos_tablet":{"unit":"px","size":0,"sizes":[]},"background_hover_xpos_mobile":{"unit":"px","size":0,"sizes":[]},"background_hover_ypos":{"unit":"px","size":0,"sizes":[]},"background_hover_ypos_tablet":{"unit":"px","size":0,"sizes":[]},"background_hover_ypos_mobile":{"unit":"px","size":0,"sizes":[]},"background_hover_bg_width":{"unit":"%","size":100,"sizes":[]},"background_hover_bg_width_tablet":{"unit":"px","size":"","sizes":[]},"background_hover_bg_width_mobile":{"unit":"px","size":"","sizes":[]},"background_hover_transition":{"unit":"px","size":0.3,"sizes":[]},"background_overlay_color_stop":{"unit":"%","size":0,"sizes":[]},"background_overlay_color_b_stop":{"unit":"%","size":100,"sizes":[]},"background_overlay_gradient_angle":{"unit":"deg","size":180,"sizes":[]},"background_overlay_xpos":{"unit":"px","size":0,"sizes":[]},"background_overlay_xpos_tablet":{"unit":"px","size":0,"sizes":[]},"background_overlay_xpos_mobile":{"unit":"px","size":0,"sizes":[]},"background_overlay_ypos":{"unit":"px","size":0,"sizes":[]},"background_overlay_ypos_tablet":{"unit":"px","size":0,"sizes":[]},"background_overlay_ypos_mobile":{"unit":"px","size":0,"sizes":[]},"background_overlay_bg_width":{"unit":"%","size":100,"sizes":[]},"background_overlay_bg_width_tablet":{"unit":"px","size":"","sizes":[]},"background_overlay_bg_width_mobile":{"unit":"px","size":"","sizes":[]},"background_overlay_opacity":{"unit":"px","size":0.5,"sizes":[]},"css_filters_blur":{"unit":"px","size":0,"sizes":[]},"css_filters_brightness":{"unit":"px","size":100,"sizes":[]},"css_filters_contrast":{"unit":"px","size":100,"sizes":[]},"css_filters_saturate":{"unit":"px","size":100,"sizes":[]},"css_filters_hue":{"unit":"px","size":0,"sizes":[]},"background_overlay_hover_color_stop":{"unit":"%","size":0,"sizes":[]},"background_overlay_hover_color_b_stop":{"unit":"%","size":100,"sizes":[]},"background_overlay_hover_gradient_angle":{"unit":"deg","size":180,"sizes":[]},"background_overlay_hover_xpos":{"unit":"px","size":0,"sizes":[]},"background_overlay_hover_xpos_tablet":{"unit":"px","size":0,"sizes":[]},"background_overlay_hover_xpos_mobile":{"unit":"px","size":0,"sizes":[]},"background_overlay_hover_ypos":{"unit":"px","size":0,"sizes":[]},"background_overlay_hover_ypos_tablet":{"unit":"px","size":0,"sizes":[]},"background_overlay_hover_ypos_mobile":{"unit":"px","size":0,"sizes":[]},"background_overlay_hover_bg_width":{"unit":"%","size":100,"sizes":[]},"background_overlay_hover_bg_width_tablet":{"unit":"px","size":"","sizes":[]},"background_overlay_hover_bg_width_mobile":{"unit":"px","size":"","sizes":[]},"background_overlay_hover_opacity":{"unit":"px","size":0.5,"sizes":[]},"css_filters_hover_blur":{"unit":"px","size":0,"sizes":[]},"css_filters_hover_brightness":{"unit":"px","size":100,"sizes":[]},"css_filters_hover_contrast":{"unit":"px","size":100,"sizes":[]},"css_filters_hover_saturate":{"unit":"px","size":100,"sizes":[]},"css_filters_hover_hue":{"unit":"px","size":0,"sizes":[]},"background_overlay_hover_transition":{"unit":"px","size":0.3,"sizes":[]},"border_hover_transition":{"unit":"px","size":0.3,"sizes":[]}},"elements":[{"id":"4732059e","settings":{"title":"New Arrivals","align":"center","typography_typography":"custom","typography_font_family":"Poppins","typography_font_size":{"unit":"px","size":30,"sizes":[]},"typography_font_weight":"500","typography_font_size_tablet":{"unit":"px","size":"","sizes":[]},"typography_font_size_mobile":{"unit":"px","size":"","sizes":[]},"typography_line_height":{"unit":"em","size":"","sizes":[]},"typography_line_height_tablet":{"unit":"em","size":"","sizes":[]},"typography_line_height_mobile":{"unit":"em","size":"","sizes":[]},"typography_letter_spacing":{"unit":"px","size":"","sizes":[]},"typography_letter_spacing_tablet":{"unit":"px","size":"","sizes":[]},"typography_letter_spacing_mobile":{"unit":"px","size":"","sizes":[]},"_background_color_stop":{"unit":"%","size":0,"sizes":[]},"_background_color_b_stop":{"unit":"%","size":100,"sizes":[]},"_background_gradient_angle":{"unit":"deg","size":180,"sizes":[]},"_background_xpos":{"unit":"px","size":0,"sizes":[]},"_background_xpos_tablet":{"unit":"px","size":0,"sizes":[]},"_background_xpos_mobile":{"unit":"px","size":0,"sizes":[]},"_background_ypos":{"unit":"px","size":0,"sizes":[]},"_background_ypos_tablet":{"unit":"px","size":0,"sizes":[]},"_background_ypos_mobile":{"unit":"px","size":0,"sizes":[]},"_background_bg_width":{"unit":"%","size":100,"sizes":[]},"_background_bg_width_tablet":{"unit":"px","size":"","sizes":[]},"_background_bg_width_mobile":{"unit":"px","size":"","sizes":[]},"_background_hover_color_stop":{"unit":"%","size":0,"sizes":[]},"_background_hover_color_b_stop":{"unit":"%","size":100,"sizes":[]},"_background_hover_gradient_angle":{"unit":"deg","size":180,"sizes":[]},"_background_hover_xpos":{"unit":"px","size":0,"sizes":[]},"_background_hover_xpos_tablet":{"unit":"px","size":0,"sizes":[]},"_background_hover_xpos_mobile":{"unit":"px","size":0,"sizes":[]},"_background_hover_ypos":{"unit":"px","size":0,"sizes":[]},"_background_hover_ypos_tablet":{"unit":"px","size":0,"sizes":[]},"_background_hover_ypos_mobile":{"unit":"px","size":0,"sizes":[]},"_background_hover_bg_width":{"unit":"%","size":100,"sizes":[]},"_background_hover_bg_width_tablet":{"unit":"px","size":"","sizes":[]},"_background_hover_bg_width_mobile":{"unit":"px","size":"","sizes":[]},"_background_hover_transition":{"unit":"px","size":"","sizes":[]},"_border_hover_transition":{"unit":"px","size":"","sizes":[]},"_element_custom_width":{"unit":"px","size":"","sizes":[]},"_element_custom_width_tablet":{"unit":"px","size":"","sizes":[]},"_element_custom_width_mobile":{"unit":"px","size":"","sizes":[]},"_offset_x":{"unit":"px","size":"0","sizes":[]},"_offset_x_tablet":{"unit":"px","size":"","sizes":[]},"_offset_x_mobile":{"unit":"px","size":"","sizes":[]},"_offset_x_end":{"unit":"px","size":"0","sizes":[]},"_offset_x_end_tablet":{"unit":"px","size":"","sizes":[]},"_offset_x_end_mobile":{"unit":"px","size":"","sizes":[]},"_offset_y":{"unit":"px","size":"0","sizes":[]},"_offset_y_tablet":{"unit":"px","size":"","sizes":[]},"_offset_y_mobile":{"unit":"px","size":"","sizes":[]},"_offset_y_end":{"unit":"px","size":"0","sizes":[]},"_offset_y_end_tablet":{"unit":"px","size":"","sizes":[]},"_offset_y_end_mobile":{"unit":"px","size":"","sizes":[]}},"elements":[],"isInner":false,"widgetType":"heading","elType":"widget"},{"id":"2ef9eb10","settings":{"title":"Contrary to popular belief, Lorem Ipsum is not simply random <br\/>text. It has roots in a piece of classical","header_size":"p","align":"center","title_color":"#5a5a5a","typography_typography":"custom","typography_font_family":"Poppins","typography_font_weight":"400","typography_line_height":{"unit":"px","size":24,"sizes":[]},"typography_font_size":{"unit":"px","size":"","sizes":[]},"typography_font_size_tablet":{"unit":"px","size":"","sizes":[]},"typography_font_size_mobile":{"unit":"px","size":"","sizes":[]},"typography_line_height_tablet":{"unit":"em","size":"","sizes":[]},"typography_line_height_mobile":{"unit":"em","size":"","sizes":[]},"typography_letter_spacing":{"unit":"px","size":"","sizes":[]},"typography_letter_spacing_tablet":{"unit":"px","size":"","sizes":[]},"typography_letter_spacing_mobile":{"unit":"px","size":"","sizes":[]},"_background_color_stop":{"unit":"%","size":0,"sizes":[]},"_background_color_b_stop":{"unit":"%","size":100,"sizes":[]},"_background_gradient_angle":{"unit":"deg","size":180,"sizes":[]},"_background_xpos":{"unit":"px","size":0,"sizes":[]},"_background_xpos_tablet":{"unit":"px","size":0,"sizes":[]},"_background_xpos_mobile":{"unit":"px","size":0,"sizes":[]},"_background_ypos":{"unit":"px","size":0,"sizes":[]},"_background_ypos_tablet":{"unit":"px","size":0,"sizes":[]},"_background_ypos_mobile":{"unit":"px","size":0,"sizes":[]},"_background_bg_width":{"unit":"%","size":100,"sizes":[]},"_background_bg_width_tablet":{"unit":"px","size":"","sizes":[]},"_background_bg_width_mobile":{"unit":"px","size":"","sizes":[]},"_background_hover_color_stop":{"unit":"%","size":0,"sizes":[]},"_background_hover_color_b_stop":{"unit":"%","size":100,"sizes":[]},"_background_hover_gradient_angle":{"unit":"deg","size":180,"sizes":[]},"_background_hover_xpos":{"unit":"px","size":0,"sizes":[]},"_background_hover_xpos_tablet":{"unit":"px","size":0,"sizes":[]},"_background_hover_xpos_mobile":{"unit":"px","size":0,"sizes":[]},"_background_hover_ypos":{"unit":"px","size":0,"sizes":[]},"_background_hover_ypos_tablet":{"unit":"px","size":0,"sizes":[]},"_background_hover_ypos_mobile":{"unit":"px","size":0,"sizes":[]},"_background_hover_bg_width":{"unit":"%","size":100,"sizes":[]},"_background_hover_bg_width_tablet":{"unit":"px","size":"","sizes":[]},"_background_hover_bg_width_mobile":{"unit":"px","size":"","sizes":[]},"_background_hover_transition":{"unit":"px","size":"","sizes":[]},"_border_hover_transition":{"unit":"px","size":"","sizes":[]},"_element_custom_width":{"unit":"px","size":"","sizes":[]},"_element_custom_width_tablet":{"unit":"px","size":"","sizes":[]},"_element_custom_width_mobile":{"unit":"px","size":"","sizes":[]},"_offset_x":{"unit":"px","size":"0","sizes":[]},"_offset_x_tablet":{"unit":"px","size":"","sizes":[]},"_offset_x_mobile":{"unit":"px","size":"","sizes":[]},"_offset_x_end":{"unit":"px","size":"0","sizes":[]},"_offset_x_end_tablet":{"unit":"px","size":"","sizes":[]},"_offset_x_end_mobile":{"unit":"px","size":"","sizes":[]},"_offset_y":{"unit":"px","size":"0","sizes":[]},"_offset_y_tablet":{"unit":"px","size":"","sizes":[]},"_offset_y_mobile":{"unit":"px","size":"","sizes":[]},"_offset_y_end":{"unit":"px","size":"0","sizes":[]},"_offset_y_end_tablet":{"unit":"px","size":"","sizes":[]},"_offset_y_end_mobile":{"unit":"px","size":"","sizes":[]}},"elements":[],"isInner":false,"widgetType":"heading","elType":"widget"},{"id":"1848ffcc","settings":{"woolentor_product_grid_column":"4","woolentor_product_grid_products_count":4,"woolentor_product_grid_categories":["accessories","decor","hoodies"],"product_content_style":"2","action_button_show_on":"hover","product_category_typography_typography":"custom","product_category_typography_font_family":"Poppins","product_category_typography_font_weight":"400","product_title_typography_typography":"custom","product_title_typography_font_family":"Poppins","product_title_typography_font_size":{"unit":"px","size":"","sizes":[]},"product_title_typography_font_weight":"400","product_sale_price_color":"#ff3535","product_sale_price_typography_typography":"custom","product_sale_price_typography_font_family":"Poppins","product_sale_price_typography_font_size":{"unit":"px","size":16,"sizes":[]},"product_sale_price_typography_font_weight":"600","product_regular_price_color":"#4a4a4a","product_regular_price_typography_typography":"custom","product_regular_price_typography_font_family":"Poppins","product_regular_price_typography_font_size":{"unit":"px","size":13,"sizes":[]},"product_regular_price_typography_font_weight":"400","tabmenutypography_typography":"custom","tabmenutypography_font_family":"Poppins","tabmenutypography_font_size":{"unit":"px","size":14,"sizes":[]},"tabmenutypography_font_weight":"400","tab_menu_color":"#1f2226","product_tab_menu_bg_color":"#f1f1f1","tabmenu_border_radius":{"unit":"px","top":"0","right":"0","bottom":"0","left":"0","isLinked":false},"tab_menu_hover_color":"#ffffff","product_tab_menu_hover_bg_color":"#1f2226","tabmenu_hover_border_border":"solid","tabmenu_hover_border_width":{"unit":"px","top":"0","right":"0","bottom":"0","left":"0","isLinked":true},"product_badge_typography_font_size":{"unit":"px","size":"","sizes":[]},"product_badge_typography_font_size_tablet":{"unit":"px","size":"","sizes":[]},"product_badge_typography_font_size_mobile":{"unit":"px","size":"","sizes":[]},"product_badge_typography_line_height":{"unit":"em","size":"","sizes":[]},"product_badge_typography_line_height_tablet":{"unit":"em","size":"","sizes":[]},"product_badge_typography_line_height_mobile":{"unit":"em","size":"","sizes":[]},"product_badge_typography_letter_spacing":{"unit":"px","size":"","sizes":[]},"product_badge_typography_letter_spacing_tablet":{"unit":"px","size":"","sizes":[]},"product_badge_typography_letter_spacing_mobile":{"unit":"px","size":"","sizes":[]},"product_category_typography_font_size":{"unit":"px","size":"","sizes":[]},"product_category_typography_font_size_tablet":{"unit":"px","size":"","sizes":[]},"product_category_typography_font_size_mobile":{"unit":"px","size":"","sizes":[]},"product_category_typography_line_height":{"unit":"em","size":"","sizes":[]},"product_category_typography_line_height_tablet":{"unit":"em","size":"","sizes":[]},"product_category_typography_line_height_mobile":{"unit":"em","size":"","sizes":[]},"product_category_typography_letter_spacing":{"unit":"px","size":"","sizes":[]},"product_category_typography_letter_spacing_tablet":{"unit":"px","size":"","sizes":[]},"product_category_typography_letter_spacing_mobile":{"unit":"px","size":"","sizes":[]},"product_title_typography_font_size_tablet":{"unit":"px","size":"","sizes":[]},"product_title_typography_font_size_mobile":{"unit":"px","size":"","sizes":[]},"product_title_typography_line_height":{"unit":"em","size":"","sizes":[]},"product_title_typography_line_height_tablet":{"unit":"em","size":"","sizes":[]},"product_title_typography_line_height_mobile":{"unit":"em","size":"","sizes":[]},"product_title_typography_letter_spacing":{"unit":"px","size":"","sizes":[]},"product_title_typography_letter_spacing_tablet":{"unit":"px","size":"","sizes":[]},"product_title_typography_letter_spacing_mobile":{"unit":"px","size":"","sizes":[]},"product_sale_price_typography_font_size_tablet":{"unit":"px","size":"","sizes":[]},"product_sale_price_typography_font_size_mobile":{"unit":"px","size":"","sizes":[]},"product_sale_price_typography_line_height":{"unit":"em","size":"","sizes":[]},"product_sale_price_typography_line_height_tablet":{"unit":"em","size":"","sizes":[]},"product_sale_price_typography_line_height_mobile":{"unit":"em","size":"","sizes":[]},"product_sale_price_typography_letter_spacing":{"unit":"px","size":"","sizes":[]},"product_sale_price_typography_letter_spacing_tablet":{"unit":"px","size":"","sizes":[]},"product_sale_price_typography_letter_spacing_mobile":{"unit":"px","size":"","sizes":[]},"product_regular_price_typography_font_size_tablet":{"unit":"px","size":"","sizes":[]},"product_regular_price_typography_font_size_mobile":{"unit":"px","size":"","sizes":[]},"product_regular_price_typography_line_height":{"unit":"em","size":"","sizes":[]},"product_regular_price_typography_line_height_tablet":{"unit":"em","size":"","sizes":[]},"product_regular_price_typography_line_height_mobile":{"unit":"em","size":"","sizes":[]},"product_regular_price_typography_letter_spacing":{"unit":"px","size":"","sizes":[]},"product_regular_price_typography_letter_spacing_tablet":{"unit":"px","size":"","sizes":[]},"product_regular_price_typography_letter_spacing_mobile":{"unit":"px","size":"","sizes":[]},"product_action_button_background_color_color_stop":{"unit":"%","size":0,"sizes":[]},"product_action_button_background_color_color_b_stop":{"unit":"%","size":100,"sizes":[]},"product_action_button_background_color_gradient_angle":{"unit":"deg","size":180,"sizes":[]},"product_action_button_background_color_xpos":{"unit":"px","size":0,"sizes":[]},"product_action_button_background_color_xpos_tablet":{"unit":"px","size":0,"sizes":[]},"product_action_button_background_color_xpos_mobile":{"unit":"px","size":0,"sizes":[]},"product_action_button_background_color_ypos":{"unit":"px","size":0,"sizes":[]},"product_action_button_background_color_ypos_tablet":{"unit":"px","size":0,"sizes":[]},"product_action_button_background_color_ypos_mobile":{"unit":"px","size":0,"sizes":[]},"product_action_button_background_color_bg_width":{"unit":"%","size":100,"sizes":[]},"product_action_button_background_color_bg_width_tablet":{"unit":"px","size":"","sizes":[]},"product_action_button_background_color_bg_width_mobile":{"unit":"px","size":"","sizes":[]},"product_action_button_tooltip_background_color_color_stop":{"unit":"%","size":0,"sizes":[]},"product_action_button_tooltip_background_color_color_b_stop":{"unit":"%","size":100,"sizes":[]},"product_action_button_tooltip_background_color_gradient_angle":{"unit":"deg","size":180,"sizes":[]},"product_action_button_tooltip_background_color_xpos":{"unit":"px","size":0,"sizes":[]},"product_action_button_tooltip_background_color_xpos_tablet":{"unit":"px","size":0,"sizes":[]},"product_action_button_tooltip_background_color_xpos_mobile":{"unit":"px","size":0,"sizes":[]},"product_action_button_tooltip_background_color_ypos":{"unit":"px","size":0,"sizes":[]},"product_action_button_tooltip_background_color_ypos_tablet":{"unit":"px","size":0,"sizes":[]},"product_action_button_tooltip_background_color_ypos_mobile":{"unit":"px","size":0,"sizes":[]},"product_action_button_tooltip_background_color_bg_width":{"unit":"%","size":100,"sizes":[]},"product_action_button_tooltip_background_color_bg_width_tablet":{"unit":"px","size":"","sizes":[]},"product_action_button_tooltip_background_color_bg_width_mobile":{"unit":"px","size":"","sizes":[]},"product_action_button_normal_background_color_color_stop":{"unit":"%","size":0,"sizes":[]},"product_action_button_normal_background_color_color_b_stop":{"unit":"%","size":100,"sizes":[]},"product_action_button_normal_background_color_gradient_angle":{"unit":"deg","size":180,"sizes":[]},"product_action_button_normal_background_color_xpos":{"unit":"px","size":0,"sizes":[]},"product_action_button_normal_background_color_xpos_tablet":{"unit":"px","size":0,"sizes":[]},"product_action_button_normal_background_color_xpos_mobile":{"unit":"px","size":0,"sizes":[]},"product_action_button_normal_background_color_ypos":{"unit":"px","size":0,"sizes":[]},"product_action_button_normal_background_color_ypos_tablet":{"unit":"px","size":0,"sizes":[]},"product_action_button_normal_background_color_ypos_mobile":{"unit":"px","size":0,"sizes":[]},"product_action_button_normal_background_color_bg_width":{"unit":"%","size":100,"sizes":[]},"product_action_button_normal_background_color_bg_width_tablet":{"unit":"px","size":"","sizes":[]},"product_action_button_normal_background_color_bg_width_mobile":{"unit":"px","size":"","sizes":[]},"product_action_button_hover_background_color_color_stop":{"unit":"%","size":0,"sizes":[]},"product_action_button_hover_background_color_color_b_stop":{"unit":"%","size":100,"sizes":[]},"product_action_button_hover_background_color_gradient_angle":{"unit":"deg","size":180,"sizes":[]},"product_action_button_hover_background_color_xpos":{"unit":"px","size":0,"sizes":[]},"product_action_button_hover_background_color_xpos_tablet":{"unit":"px","size":0,"sizes":[]},"product_action_button_hover_background_color_xpos_mobile":{"unit":"px","size":0,"sizes":[]},"product_action_button_hover_background_color_ypos":{"unit":"px","size":0,"sizes":[]},"product_action_button_hover_background_color_ypos_tablet":{"unit":"px","size":0,"sizes":[]},"product_action_button_hover_background_color_ypos_mobile":{"unit":"px","size":0,"sizes":[]},"product_action_button_hover_background_color_bg_width":{"unit":"%","size":100,"sizes":[]},"product_action_button_hover_background_color_bg_width_tablet":{"unit":"px","size":"","sizes":[]},"product_action_button_hover_background_color_bg_width_mobile":{"unit":"px","size":"","sizes":[]},"product_counter_background_color_color_stop":{"unit":"%","size":0,"sizes":[]},"product_counter_background_color_color_b_stop":{"unit":"%","size":100,"sizes":[]},"product_counter_background_color_gradient_angle":{"unit":"deg","size":180,"sizes":[]},"product_counter_background_color_xpos":{"unit":"px","size":0,"sizes":[]},"product_counter_background_color_xpos_tablet":{"unit":"px","size":0,"sizes":[]},"product_counter_background_color_xpos_mobile":{"unit":"px","size":0,"sizes":[]},"product_counter_background_color_ypos":{"unit":"px","size":0,"sizes":[]},"product_counter_background_color_ypos_tablet":{"unit":"px","size":0,"sizes":[]},"product_counter_background_color_ypos_mobile":{"unit":"px","size":0,"sizes":[]},"product_counter_background_color_bg_width":{"unit":"%","size":100,"sizes":[]},"product_counter_background_color_bg_width_tablet":{"unit":"px","size":"","sizes":[]},"product_counter_background_color_bg_width_mobile":{"unit":"px","size":"","sizes":[]},"tabmenutypography_font_size_tablet":{"unit":"px","size":"","sizes":[]},"tabmenutypography_font_size_mobile":{"unit":"px","size":"","sizes":[]},"tabmenutypography_line_height":{"unit":"em","size":"","sizes":[]},"tabmenutypography_line_height_tablet":{"unit":"em","size":"","sizes":[]},"tabmenutypography_line_height_mobile":{"unit":"em","size":"","sizes":[]},"tabmenutypography_letter_spacing":{"unit":"px","size":"","sizes":[]},"tabmenutypography_letter_spacing_tablet":{"unit":"px","size":"","sizes":[]},"tabmenutypography_letter_spacing_mobile":{"unit":"px","size":"","sizes":[]},"tabmenu_border_border":"solid","tabmenu_border_width":{"unit":"px","top":"0","right":"0","bottom":"0","left":"0","isLinked":true},"_background_color_stop":{"unit":"%","size":0,"sizes":[]},"_background_color_b_stop":{"unit":"%","size":100,"sizes":[]},"_background_gradient_angle":{"unit":"deg","size":180,"sizes":[]},"_background_xpos":{"unit":"px","size":0,"sizes":[]},"_background_xpos_tablet":{"unit":"px","size":0,"sizes":[]},"_background_xpos_mobile":{"unit":"px","size":0,"sizes":[]},"_background_ypos":{"unit":"px","size":0,"sizes":[]},"_background_ypos_tablet":{"unit":"px","size":0,"sizes":[]},"_background_ypos_mobile":{"unit":"px","size":0,"sizes":[]},"_background_bg_width":{"unit":"%","size":100,"sizes":[]},"_background_bg_width_tablet":{"unit":"px","size":"","sizes":[]},"_background_bg_width_mobile":{"unit":"px","size":"","sizes":[]},"_background_hover_color_stop":{"unit":"%","size":0,"sizes":[]},"_background_hover_color_b_stop":{"unit":"%","size":100,"sizes":[]},"_background_hover_gradient_angle":{"unit":"deg","size":180,"sizes":[]},"_background_hover_xpos":{"unit":"px","size":0,"sizes":[]},"_background_hover_xpos_tablet":{"unit":"px","size":0,"sizes":[]},"_background_hover_xpos_mobile":{"unit":"px","size":0,"sizes":[]},"_background_hover_ypos":{"unit":"px","size":0,"sizes":[]},"_background_hover_ypos_tablet":{"unit":"px","size":0,"sizes":[]},"_background_hover_ypos_mobile":{"unit":"px","size":0,"sizes":[]},"_background_hover_bg_width":{"unit":"%","size":100,"sizes":[]},"_background_hover_bg_width_tablet":{"unit":"px","size":"","sizes":[]},"_background_hover_bg_width_mobile":{"unit":"px","size":"","sizes":[]},"_background_hover_transition":{"unit":"px","size":"","sizes":[]},"_border_hover_transition":{"unit":"px","size":"","sizes":[]},"_element_custom_width":{"unit":"px","size":"","sizes":[]},"_element_custom_width_tablet":{"unit":"px","size":"","sizes":[]},"_element_custom_width_mobile":{"unit":"px","size":"","sizes":[]},"_offset_x":{"unit":"px","size":"0","sizes":[]},"_offset_x_tablet":{"unit":"px","size":"","sizes":[]},"_offset_x_mobile":{"unit":"px","size":"","sizes":[]},"_offset_x_end":{"unit":"px","size":"0","sizes":[]},"_offset_x_end_tablet":{"unit":"px","size":"","sizes":[]},"_offset_x_end_mobile":{"unit":"px","size":"","sizes":[]},"_offset_y":{"unit":"px","size":"0","sizes":[]},"_offset_y_tablet":{"unit":"px","size":"","sizes":[]},"_offset_y_mobile":{"unit":"px","size":"","sizes":[]},"_offset_y_end":{"unit":"px","size":"0","sizes":[]},"_offset_y_end_tablet":{"unit":"px","size":"","sizes":[]},"_offset_y_end_mobile":{"unit":"px","size":"","sizes":[]}},"elements":[],"isInner":false,"widgetType":"woolentor-universal-product","elType":"widget"}],"isInner":false,"elType":"column"}],"isInner":false,"elType":"section"},{"id":"3769dc32","settings":{"structure":"20","margin":{"unit":"px","top":"60","right":0,"bottom":"90","left":0,"isLinked":false}},"elements":[{"id":"30fd4790","settings":{"_column_size":50,"_inline_size":null},"elements":[{"id":"198980c8","settings":{"bannerimage":{"url":"","id":""},"bannerimagesize_size":"full","bannersubtitle":"Black Monday","bannertitle":"Wooden Lamp<br\/>\nSave 30%","buttontxt":"Shop Now","buttonlink":{"url":"#","is_external":true,"nofollow":true},"_background_background":"classic","_background_color":"#fbf8eb","_background_color_stop":{"unit":"%","size":0,"sizes":[]},"_background_color_b_stop":{"unit":"%","size":100,"sizes":[]},"_background_gradient_angle":{"unit":"deg","size":180,"sizes":[]},"_background_xpos":{"unit":"px","size":0,"sizes":[]},"_background_xpos_tablet":{"unit":"px","size":0,"sizes":[]},"_background_xpos_mobile":{"unit":"px","size":0,"sizes":[]},"_background_ypos":{"unit":"px","size":0,"sizes":[]},"_background_ypos_tablet":{"unit":"px","size":0,"sizes":[]},"_background_ypos_mobile":{"unit":"px","size":0,"sizes":[]},"_background_bg_width":{"unit":"%","size":100,"sizes":[]},"_background_bg_width_tablet":{"unit":"px","size":"","sizes":[]},"_background_bg_width_mobile":{"unit":"px","size":"","sizes":[]},"_background_hover_color_stop":{"unit":"%","size":0,"sizes":[]},"_background_hover_color_b_stop":{"unit":"%","size":100,"sizes":[]},"_background_hover_gradient_angle":{"unit":"deg","size":180,"sizes":[]},"_background_hover_xpos":{"unit":"px","size":0,"sizes":[]},"_background_hover_xpos_tablet":{"unit":"px","size":0,"sizes":[]},"_background_hover_xpos_mobile":{"unit":"px","size":0,"sizes":[]},"_background_hover_ypos":{"unit":"px","size":0,"sizes":[]},"_background_hover_ypos_tablet":{"unit":"px","size":0,"sizes":[]},"_background_hover_ypos_mobile":{"unit":"px","size":0,"sizes":[]},"_background_hover_bg_width":{"unit":"%","size":100,"sizes":[]},"_background_hover_bg_width_tablet":{"unit":"px","size":"","sizes":[]},"_background_hover_bg_width_mobile":{"unit":"px","size":"","sizes":[]},"_background_hover_transition":{"unit":"px","size":"","sizes":[]},"_border_hover_transition":{"unit":"px","size":"","sizes":[]},"_element_custom_width":{"unit":"px","size":"","sizes":[]},"_element_custom_width_tablet":{"unit":"px","size":"","sizes":[]},"_element_custom_width_mobile":{"unit":"px","size":"","sizes":[]},"_offset_x":{"unit":"px","size":"0","sizes":[]},"_offset_x_tablet":{"unit":"px","size":"","sizes":[]},"_offset_x_mobile":{"unit":"px","size":"","sizes":[]},"_offset_x_end":{"unit":"px","size":"0","sizes":[]},"_offset_x_end_tablet":{"unit":"px","size":"","sizes":[]},"_offset_x_end_mobile":{"unit":"px","size":"","sizes":[]},"_offset_y":{"unit":"px","size":"0","sizes":[]},"_offset_y_tablet":{"unit":"px","size":"","sizes":[]},"_offset_y_mobile":{"unit":"px","size":"","sizes":[]},"_offset_y_end":{"unit":"px","size":"0","sizes":[]},"_offset_y_end_tablet":{"unit":"px","size":"","sizes":[]},"_offset_y_end_mobile":{"unit":"px","size":"","sizes":[]},"title_typography_typography":"custom","title_typography_font_family":"Poppins","title_typography_font_weight":"400","sub_title_typography_typography":"custom","sub_title_typography_font_family":"Poppins","sub_title_typography_font_weight":"500","content_alignment":"right","title_typography_font_size":{"unit":"px","size":"","sizes":[]},"title_typography_font_size_tablet":{"unit":"px","size":16,"sizes":[]},"title_typography_font_size_mobile":{"unit":"px","size":"","sizes":[]},"title_typography_line_height":{"unit":"em","size":"","sizes":[]},"title_typography_line_height_tablet":{"unit":"em","size":"","sizes":[]},"title_typography_line_height_mobile":{"unit":"em","size":"","sizes":[]},"title_typography_letter_spacing":{"unit":"px","size":"","sizes":[]},"title_typography_letter_spacing_tablet":{"unit":"px","size":"","sizes":[]},"title_typography_letter_spacing_mobile":{"unit":"px","size":"","sizes":[]},"sub_title_typography_font_size":{"unit":"px","size":"","sizes":[]},"sub_title_typography_font_size_tablet":{"unit":"px","size":"","sizes":[]},"sub_title_typography_font_size_mobile":{"unit":"px","size":"","sizes":[]},"sub_title_typography_line_height":{"unit":"em","size":"","sizes":[]},"sub_title_typography_line_height_tablet":{"unit":"em","size":"","sizes":[]},"sub_title_typography_line_height_mobile":{"unit":"em","size":"","sizes":[]},"sub_title_typography_letter_spacing":{"unit":"px","size":"","sizes":[]},"sub_title_typography_letter_spacing_tablet":{"unit":"px","size":"","sizes":[]},"sub_title_typography_letter_spacing_mobile":{"unit":"px","size":"","sizes":[]},"button_typography_font_size":{"unit":"px","size":"","sizes":[]},"button_typography_font_size_tablet":{"unit":"px","size":"","sizes":[]},"button_typography_font_size_mobile":{"unit":"px","size":"","sizes":[]},"button_typography_line_height":{"unit":"em","size":"","sizes":[]},"button_typography_line_height_tablet":{"unit":"em","size":"","sizes":[]},"button_typography_line_height_mobile":{"unit":"em","size":"","sizes":[]},"button_typography_letter_spacing":{"unit":"px","size":"","sizes":[]},"button_typography_letter_spacing_tablet":{"unit":"px","size":"","sizes":[]},"button_typography_letter_spacing_mobile":{"unit":"px","size":"","sizes":[]},"_padding":{"unit":"px","top":"60","right":"0","bottom":"60","left":"0","isLinked":false},"_background_image":{"url":"http:\/\/demo.shrimpthemes.com\/1\/parlo\/wp-content\/uploads\/2019\/03\/banner_4.png","id":177},"_background_repeat":"no-repeat","_background_size":"cover"},"elements":[],"isInner":false,"widgetType":"woolentor-addbanner-addons","elType":"widget"}],"isInner":false,"elType":"column"},{"id":"6133773d","settings":{"_column_size":50,"_inline_size":null},"elements":[{"id":"66e71947","settings":{"bannerimage":{"url":"","id":""},"bannerimagesize_size":"full","bannersubtitle":"Black Friday","bannertitle":"Watch & Lamp<br\/>\nSave 15%","buttontxt":"Shop Now","buttonlink":{"url":"#","is_external":true,"nofollow":true},"_background_background":"classic","_background_color_stop":{"unit":"%","size":0,"sizes":[]},"_background_color_b_stop":{"unit":"%","size":100,"sizes":[]},"_background_gradient_angle":{"unit":"deg","size":180,"sizes":[]},"_background_xpos":{"unit":"px","size":0,"sizes":[]},"_background_xpos_tablet":{"unit":"px","size":0,"sizes":[]},"_background_xpos_mobile":{"unit":"px","size":0,"sizes":[]},"_background_ypos":{"unit":"px","size":0,"sizes":[]},"_background_ypos_tablet":{"unit":"px","size":0,"sizes":[]},"_background_ypos_mobile":{"unit":"px","size":0,"sizes":[]},"_background_bg_width":{"unit":"%","size":100,"sizes":[]},"_background_bg_width_tablet":{"unit":"px","size":"","sizes":[]},"_background_bg_width_mobile":{"unit":"px","size":"","sizes":[]},"_background_hover_color_stop":{"unit":"%","size":0,"sizes":[]},"_background_hover_color_b_stop":{"unit":"%","size":100,"sizes":[]},"_background_hover_gradient_angle":{"unit":"deg","size":180,"sizes":[]},"_background_hover_xpos":{"unit":"px","size":0,"sizes":[]},"_background_hover_xpos_tablet":{"unit":"px","size":0,"sizes":[]},"_background_hover_xpos_mobile":{"unit":"px","size":0,"sizes":[]},"_background_hover_ypos":{"unit":"px","size":0,"sizes":[]},"_background_hover_ypos_tablet":{"unit":"px","size":0,"sizes":[]},"_background_hover_ypos_mobile":{"unit":"px","size":0,"sizes":[]},"_background_hover_bg_width":{"unit":"%","size":100,"sizes":[]},"_background_hover_bg_width_tablet":{"unit":"px","size":"","sizes":[]},"_background_hover_bg_width_mobile":{"unit":"px","size":"","sizes":[]},"_background_hover_transition":{"unit":"px","size":"","sizes":[]},"_border_hover_transition":{"unit":"px","size":"","sizes":[]},"_element_custom_width":{"unit":"px","size":"","sizes":[]},"_element_custom_width_tablet":{"unit":"px","size":"","sizes":[]},"_element_custom_width_mobile":{"unit":"px","size":"","sizes":[]},"_offset_x":{"unit":"px","size":"0","sizes":[]},"_offset_x_tablet":{"unit":"px","size":"","sizes":[]},"_offset_x_mobile":{"unit":"px","size":"","sizes":[]},"_offset_x_end":{"unit":"px","size":"0","sizes":[]},"_offset_x_end_tablet":{"unit":"px","size":"","sizes":[]},"_offset_x_end_mobile":{"unit":"px","size":"","sizes":[]},"_offset_y":{"unit":"px","size":"0","sizes":[]},"_offset_y_tablet":{"unit":"px","size":"","sizes":[]},"_offset_y_mobile":{"unit":"px","size":"","sizes":[]},"_offset_y_end":{"unit":"px","size":"0","sizes":[]},"_offset_y_end_tablet":{"unit":"px","size":"","sizes":[]},"_offset_y_end_mobile":{"unit":"px","size":"","sizes":[]},"title_typography_typography":"custom","title_typography_font_family":"Poppins","title_typography_font_weight":"400","sub_title_typography_typography":"custom","sub_title_typography_font_family":"Poppins","sub_title_typography_font_weight":"500","title_typography_font_size":{"unit":"px","size":"","sizes":[]},"title_typography_font_size_tablet":{"unit":"px","size":16,"sizes":[]},"title_typography_font_size_mobile":{"unit":"px","size":"","sizes":[]},"title_typography_line_height":{"unit":"em","size":"","sizes":[]},"title_typography_line_height_tablet":{"unit":"em","size":"","sizes":[]},"title_typography_line_height_mobile":{"unit":"em","size":"","sizes":[]},"title_typography_letter_spacing":{"unit":"px","size":"","sizes":[]},"title_typography_letter_spacing_tablet":{"unit":"px","size":"","sizes":[]},"title_typography_letter_spacing_mobile":{"unit":"px","size":"","sizes":[]},"sub_title_typography_font_size":{"unit":"px","size":"","sizes":[]},"sub_title_typography_font_size_tablet":{"unit":"px","size":14,"sizes":[]},"sub_title_typography_font_size_mobile":{"unit":"px","size":"","sizes":[]},"sub_title_typography_line_height":{"unit":"em","size":"","sizes":[]},"sub_title_typography_line_height_tablet":{"unit":"em","size":"","sizes":[]},"sub_title_typography_line_height_mobile":{"unit":"em","size":"","sizes":[]},"sub_title_typography_letter_spacing":{"unit":"px","size":"","sizes":[]},"sub_title_typography_letter_spacing_tablet":{"unit":"px","size":"","sizes":[]},"sub_title_typography_letter_spacing_mobile":{"unit":"px","size":"","sizes":[]},"button_typography_font_size":{"unit":"px","size":"","sizes":[]},"button_typography_font_size_tablet":{"unit":"px","size":"","sizes":[]},"button_typography_font_size_mobile":{"unit":"px","size":"","sizes":[]},"button_typography_line_height":{"unit":"em","size":"","sizes":[]},"button_typography_line_height_tablet":{"unit":"em","size":"","sizes":[]},"button_typography_line_height_mobile":{"unit":"em","size":"","sizes":[]},"button_typography_letter_spacing":{"unit":"px","size":"","sizes":[]},"button_typography_letter_spacing_tablet":{"unit":"px","size":"","sizes":[]},"button_typography_letter_spacing_mobile":{"unit":"px","size":"","sizes":[]},"_padding":{"unit":"px","top":"60","right":"0","bottom":"60","left":"0","isLinked":false},"_background_image":{"url":"http:\/\/demo.shrimpthemes.com\/1\/parlo\/wp-content\/uploads\/2019\/03\/banner_5.png","id":181},"_background_repeat":"no-repeat","_background_size":"cover"},"elements":[],"isInner":false,"widgetType":"woolentor-addbanner-addons","elType":"widget"}],"isInner":false,"elType":"column"}],"isInner":false,"elType":"section"},{"id":"5f45de8a","settings":{"structure":"30","padding":{"unit":"px","top":"30","right":"0","bottom":"90","left":"0","isLinked":false}},"elements":[{"id":"3df867df","settings":{"_column_size":33,"_inline_size":null},"elements":[{"id":"64d9d811","settings":{"serviceimage":{"url":"http:\/\/demo.shrimpthemes.com\/1\/parlo\/wp-content\/uploads\/2019\/03\/service_1.png","id":202},"serviceimagesize_size":"full","servicetitle":"Free Shipping","servicecontent":"Most product are free<br\/>\nshipping.","service_title_typography_typography":"custom","service_title_typography_font_family":"Poppins","service_desc_typography_typography":"custom","service_desc_typography_font_family":"Poppins","service_desc_typography_font_weight":"400"},"elements":[],"isInner":false,"widgetType":"parlo-service-addons","elType":"widget"}],"isInner":false,"elType":"column"},{"id":"3bf322e","settings":{"_column_size":33,"_inline_size":null},"elements":[{"id":"37b0e3c7","settings":{"serviceimage":{"url":"http:\/\/demo.shrimpthemes.com\/1\/parlo\/wp-content\/uploads\/2019\/03\/service_2.png","id":205},"serviceimagesize_size":"full","servicetitle":"Customer Support","servicecontent":"24x7 Customer Support","service_title_typography_typography":"custom","service_title_typography_font_family":"Poppins","service_title_typography_font_size":{"unit":"px","size":"","sizes":[]},"service_title_typography_font_size_tablet":{"unit":"px","size":"","sizes":[]},"service_title_typography_font_size_mobile":{"unit":"px","size":"","sizes":[]},"service_title_typography_line_height":{"unit":"em","size":"","sizes":[]},"service_title_typography_line_height_tablet":{"unit":"em","size":"","sizes":[]},"service_title_typography_line_height_mobile":{"unit":"em","size":"","sizes":[]},"service_title_typography_letter_spacing":{"unit":"px","size":"","sizes":[]},"service_title_typography_letter_spacing_tablet":{"unit":"px","size":"","sizes":[]},"service_title_typography_letter_spacing_mobile":{"unit":"px","size":"","sizes":[]},"service_desc_typography_typography":"custom","service_desc_typography_font_family":"Poppins","service_desc_typography_font_size":{"unit":"px","size":"","sizes":[]},"service_desc_typography_font_size_tablet":{"unit":"px","size":"","sizes":[]},"service_desc_typography_font_size_mobile":{"unit":"px","size":"","sizes":[]},"service_desc_typography_font_weight":"400","service_desc_typography_line_height":{"unit":"em","size":"","sizes":[]},"service_desc_typography_line_height_tablet":{"unit":"em","size":"","sizes":[]},"service_desc_typography_line_height_mobile":{"unit":"em","size":"","sizes":[]},"service_desc_typography_letter_spacing":{"unit":"px","size":"","sizes":[]},"service_desc_typography_letter_spacing_tablet":{"unit":"px","size":"","sizes":[]},"service_desc_typography_letter_spacing_mobile":{"unit":"px","size":"","sizes":[]},"_background_color_stop":{"unit":"%","size":0,"sizes":[]},"_background_color_b_stop":{"unit":"%","size":100,"sizes":[]},"_background_gradient_angle":{"unit":"deg","size":180,"sizes":[]},"_background_xpos":{"unit":"px","size":0,"sizes":[]},"_background_xpos_tablet":{"unit":"px","size":0,"sizes":[]},"_background_xpos_mobile":{"unit":"px","size":0,"sizes":[]},"_background_ypos":{"unit":"px","size":0,"sizes":[]},"_background_ypos_tablet":{"unit":"px","size":0,"sizes":[]},"_background_ypos_mobile":{"unit":"px","size":0,"sizes":[]},"_background_bg_width":{"unit":"%","size":100,"sizes":[]},"_background_bg_width_tablet":{"unit":"px","size":"","sizes":[]},"_background_bg_width_mobile":{"unit":"px","size":"","sizes":[]},"_background_hover_color_stop":{"unit":"%","size":0,"sizes":[]},"_background_hover_color_b_stop":{"unit":"%","size":100,"sizes":[]},"_background_hover_gradient_angle":{"unit":"deg","size":180,"sizes":[]},"_background_hover_xpos":{"unit":"px","size":0,"sizes":[]},"_background_hover_xpos_tablet":{"unit":"px","size":0,"sizes":[]},"_background_hover_xpos_mobile":{"unit":"px","size":0,"sizes":[]},"_background_hover_ypos":{"unit":"px","size":0,"sizes":[]},"_background_hover_ypos_tablet":{"unit":"px","size":0,"sizes":[]},"_background_hover_ypos_mobile":{"unit":"px","size":0,"sizes":[]},"_background_hover_bg_width":{"unit":"%","size":100,"sizes":[]},"_background_hover_bg_width_tablet":{"unit":"px","size":"","sizes":[]},"_background_hover_bg_width_mobile":{"unit":"px","size":"","sizes":[]},"_background_hover_transition":{"unit":"px","size":"","sizes":[]},"_border_hover_transition":{"unit":"px","size":"","sizes":[]},"_element_custom_width":{"unit":"px","size":"","sizes":[]},"_element_custom_width_tablet":{"unit":"px","size":"","sizes":[]},"_element_custom_width_mobile":{"unit":"px","size":"","sizes":[]},"_offset_x":{"unit":"px","size":"0","sizes":[]},"_offset_x_tablet":{"unit":"px","size":"","sizes":[]},"_offset_x_mobile":{"unit":"px","size":"","sizes":[]},"_offset_x_end":{"unit":"px","size":"0","sizes":[]},"_offset_x_end_tablet":{"unit":"px","size":"","sizes":[]},"_offset_x_end_mobile":{"unit":"px","size":"","sizes":[]},"_offset_y":{"unit":"px","size":"0","sizes":[]},"_offset_y_tablet":{"unit":"px","size":"","sizes":[]},"_offset_y_mobile":{"unit":"px","size":"","sizes":[]},"_offset_y_end":{"unit":"px","size":"0","sizes":[]},"_offset_y_end_tablet":{"unit":"px","size":"","sizes":[]},"_offset_y_end_mobile":{"unit":"px","size":"","sizes":[]}},"elements":[],"isInner":false,"widgetType":"parlo-service-addons","elType":"widget"}],"isInner":false,"elType":"column"},{"id":"372d6485","settings":{"_column_size":33,"_inline_size":null},"elements":[{"id":"534b5371","settings":{"serviceimage":{"url":"http:\/\/demo.shrimpthemes.com\/1\/parlo\/wp-content\/uploads\/2019\/03\/service_1.png","id":202},"serviceimagesize_size":"full","servicetitle":"Secure Payment","servicecontent":"Most Secure Payment<br\/>\nfor customer.","service_title_typography_typography":"custom","service_title_typography_font_family":"Poppins","service_title_typography_font_size":{"unit":"px","size":"","sizes":[]},"service_title_typography_font_size_tablet":{"unit":"px","size":"","sizes":[]},"service_title_typography_font_size_mobile":{"unit":"px","size":"","sizes":[]},"service_title_typography_line_height":{"unit":"em","size":"","sizes":[]},"service_title_typography_line_height_tablet":{"unit":"em","size":"","sizes":[]},"service_title_typography_line_height_mobile":{"unit":"em","size":"","sizes":[]},"service_title_typography_letter_spacing":{"unit":"px","size":"","sizes":[]},"service_title_typography_letter_spacing_tablet":{"unit":"px","size":"","sizes":[]},"service_title_typography_letter_spacing_mobile":{"unit":"px","size":"","sizes":[]},"service_desc_typography_typography":"custom","service_desc_typography_font_family":"Poppins","service_desc_typography_font_size":{"unit":"px","size":"","sizes":[]},"service_desc_typography_font_size_tablet":{"unit":"px","size":"","sizes":[]},"service_desc_typography_font_size_mobile":{"unit":"px","size":"","sizes":[]},"service_desc_typography_font_weight":"400","service_desc_typography_line_height":{"unit":"em","size":"","sizes":[]},"service_desc_typography_line_height_tablet":{"unit":"em","size":"","sizes":[]},"service_desc_typography_line_height_mobile":{"unit":"em","size":"","sizes":[]},"service_desc_typography_letter_spacing":{"unit":"px","size":"","sizes":[]},"service_desc_typography_letter_spacing_tablet":{"unit":"px","size":"","sizes":[]},"service_desc_typography_letter_spacing_mobile":{"unit":"px","size":"","sizes":[]},"_background_color_stop":{"unit":"%","size":0,"sizes":[]},"_background_color_b_stop":{"unit":"%","size":100,"sizes":[]},"_background_gradient_angle":{"unit":"deg","size":180,"sizes":[]},"_background_xpos":{"unit":"px","size":0,"sizes":[]},"_background_xpos_tablet":{"unit":"px","size":0,"sizes":[]},"_background_xpos_mobile":{"unit":"px","size":0,"sizes":[]},"_background_ypos":{"unit":"px","size":0,"sizes":[]},"_background_ypos_tablet":{"unit":"px","size":0,"sizes":[]},"_background_ypos_mobile":{"unit":"px","size":0,"sizes":[]},"_background_bg_width":{"unit":"%","size":100,"sizes":[]},"_background_bg_width_tablet":{"unit":"px","size":"","sizes":[]},"_background_bg_width_mobile":{"unit":"px","size":"","sizes":[]},"_background_hover_color_stop":{"unit":"%","size":0,"sizes":[]},"_background_hover_color_b_stop":{"unit":"%","size":100,"sizes":[]},"_background_hover_gradient_angle":{"unit":"deg","size":180,"sizes":[]},"_background_hover_xpos":{"unit":"px","size":0,"sizes":[]},"_background_hover_xpos_tablet":{"unit":"px","size":0,"sizes":[]},"_background_hover_xpos_mobile":{"unit":"px","size":0,"sizes":[]},"_background_hover_ypos":{"unit":"px","size":0,"sizes":[]},"_background_hover_ypos_tablet":{"unit":"px","size":0,"sizes":[]},"_background_hover_ypos_mobile":{"unit":"px","size":0,"sizes":[]},"_background_hover_bg_width":{"unit":"%","size":100,"sizes":[]},"_background_hover_bg_width_tablet":{"unit":"px","size":"","sizes":[]},"_background_hover_bg_width_mobile":{"unit":"px","size":"","sizes":[]},"_background_hover_transition":{"unit":"px","size":"","sizes":[]},"_border_hover_transition":{"unit":"px","size":"","sizes":[]},"_element_custom_width":{"unit":"px","size":"","sizes":[]},"_element_custom_width_tablet":{"unit":"px","size":"","sizes":[]},"_element_custom_width_mobile":{"unit":"px","size":"","sizes":[]},"_offset_x":{"unit":"px","size":"0","sizes":[]},"_offset_x_tablet":{"unit":"px","size":"","sizes":[]},"_offset_x_mobile":{"unit":"px","size":"","sizes":[]},"_offset_x_end":{"unit":"px","size":"0","sizes":[]},"_offset_x_end_tablet":{"unit":"px","size":"","sizes":[]},"_offset_x_end_mobile":{"unit":"px","size":"","sizes":[]},"_offset_y":{"unit":"px","size":"0","sizes":[]},"_offset_y_tablet":{"unit":"px","size":"","sizes":[]},"_offset_y_mobile":{"unit":"px","size":"","sizes":[]},"_offset_y_end":{"unit":"px","size":"0","sizes":[]},"_offset_y_end_tablet":{"unit":"px","size":"","sizes":[]},"_offset_y_end_mobile":{"unit":"px","size":"","sizes":[]}},"elements":[],"isInner":false,"widgetType":"parlo-service-addons","elType":"widget"}],"isInner":false,"elType":"column"}],"isInner":false,"elType":"section"},{"id":"2ae98077","settings":{"content_width":{"unit":"px","size":"","sizes":[]},"custom_height":{"unit":"px","size":400,"sizes":[]},"custom_height_tablet":{"unit":"px","size":"","sizes":[]},"custom_height_mobile":{"unit":"px","size":"","sizes":[]},"background_color_stop":{"unit":"%","size":0,"sizes":[]},"background_color_b_stop":{"unit":"%","size":100,"sizes":[]},"background_gradient_angle":{"unit":"deg","size":180,"sizes":[]},"background_xpos":{"unit":"px","size":0,"sizes":[]},"background_xpos_tablet":{"unit":"px","size":0,"sizes":[]},"background_xpos_mobile":{"unit":"px","size":0,"sizes":[]},"background_ypos":{"unit":"px","size":0,"sizes":[]},"background_ypos_tablet":{"unit":"px","size":0,"sizes":[]},"background_ypos_mobile":{"unit":"px","size":0,"sizes":[]},"background_bg_width":{"unit":"%","size":100,"sizes":[]},"background_bg_width_tablet":{"unit":"px","size":"","sizes":[]},"background_bg_width_mobile":{"unit":"px","size":"","sizes":[]},"background_hover_color_stop":{"unit":"%","size":0,"sizes":[]},"background_hover_color_b_stop":{"unit":"%","size":100,"sizes":[]},"background_hover_gradient_angle":{"unit":"deg","size":180,"sizes":[]},"background_hover_xpos":{"unit":"px","size":0,"sizes":[]},"background_hover_xpos_tablet":{"unit":"px","size":0,"sizes":[]},"background_hover_xpos_mobile":{"unit":"px","size":0,"sizes":[]},"background_hover_ypos":{"unit":"px","size":0,"sizes":[]},"background_hover_ypos_tablet":{"unit":"px","size":0,"sizes":[]},"background_hover_ypos_mobile":{"unit":"px","size":0,"sizes":[]},"background_hover_bg_width":{"unit":"%","size":100,"sizes":[]},"background_hover_bg_width_tablet":{"unit":"px","size":"","sizes":[]},"background_hover_bg_width_mobile":{"unit":"px","size":"","sizes":[]},"background_hover_transition":{"unit":"px","size":0.3,"sizes":[]},"background_overlay_color_stop":{"unit":"%","size":0,"sizes":[]},"background_overlay_color_b_stop":{"unit":"%","size":100,"sizes":[]},"background_overlay_gradient_angle":{"unit":"deg","size":180,"sizes":[]},"background_overlay_xpos":{"unit":"px","size":0,"sizes":[]},"background_overlay_xpos_tablet":{"unit":"px","size":0,"sizes":[]},"background_overlay_xpos_mobile":{"unit":"px","size":0,"sizes":[]},"background_overlay_ypos":{"unit":"px","size":0,"sizes":[]},"background_overlay_ypos_tablet":{"unit":"px","size":0,"sizes":[]},"background_overlay_ypos_mobile":{"unit":"px","size":0,"sizes":[]},"background_overlay_bg_width":{"unit":"%","size":100,"sizes":[]},"background_overlay_bg_width_tablet":{"unit":"px","size":"","sizes":[]},"background_overlay_bg_width_mobile":{"unit":"px","size":"","sizes":[]},"background_overlay_opacity":{"unit":"px","size":0.5,"sizes":[]},"css_filters_blur":{"unit":"px","size":0,"sizes":[]},"css_filters_brightness":{"unit":"px","size":100,"sizes":[]},"css_filters_contrast":{"unit":"px","size":100,"sizes":[]},"css_filters_saturate":{"unit":"px","size":100,"sizes":[]},"css_filters_hue":{"unit":"px","size":0,"sizes":[]},"background_overlay_hover_color_stop":{"unit":"%","size":0,"sizes":[]},"background_overlay_hover_color_b_stop":{"unit":"%","size":100,"sizes":[]},"background_overlay_hover_gradient_angle":{"unit":"deg","size":180,"sizes":[]},"background_overlay_hover_xpos":{"unit":"px","size":0,"sizes":[]},"background_overlay_hover_xpos_tablet":{"unit":"px","size":0,"sizes":[]},"background_overlay_hover_xpos_mobile":{"unit":"px","size":0,"sizes":[]},"background_overlay_hover_ypos":{"unit":"px","size":0,"sizes":[]},"background_overlay_hover_ypos_tablet":{"unit":"px","size":0,"sizes":[]},"background_overlay_hover_ypos_mobile":{"unit":"px","size":0,"sizes":[]},"background_overlay_hover_bg_width":{"unit":"%","size":100,"sizes":[]},"background_overlay_hover_bg_width_tablet":{"unit":"px","size":"","sizes":[]},"background_overlay_hover_bg_width_mobile":{"unit":"px","size":"","sizes":[]},"background_overlay_hover_opacity":{"unit":"px","size":0.5,"sizes":[]},"css_filters_hover_blur":{"unit":"px","size":0,"sizes":[]},"css_filters_hover_brightness":{"unit":"px","size":100,"sizes":[]},"css_filters_hover_contrast":{"unit":"px","size":100,"sizes":[]},"css_filters_hover_saturate":{"unit":"px","size":100,"sizes":[]},"css_filters_hover_hue":{"unit":"px","size":0,"sizes":[]},"background_overlay_hover_transition":{"unit":"px","size":0.3,"sizes":[]},"border_hover_transition":{"unit":"px","size":0.3,"sizes":[]},"shape_divider_top_width":{"unit":"%","size":"","sizes":[]},"shape_divider_top_width_tablet":{"unit":"%","size":"","sizes":[]},"shape_divider_top_width_mobile":{"unit":"%","size":"","sizes":[]},"shape_divider_top_height":{"unit":"px","size":"","sizes":[]},"shape_divider_top_height_tablet":{"unit":"px","size":"","sizes":[]},"shape_divider_top_height_mobile":{"unit":"px","size":"","sizes":[]},"shape_divider_bottom_width":{"unit":"%","size":"","sizes":[]},"shape_divider_bottom_width_tablet":{"unit":"%","size":"","sizes":[]},"shape_divider_bottom_width_mobile":{"unit":"%","size":"","sizes":[]},"shape_divider_bottom_height":{"unit":"px","size":"","sizes":[]},"shape_divider_bottom_height_tablet":{"unit":"px","size":"","sizes":[]},"shape_divider_bottom_height_mobile":{"unit":"px","size":"","sizes":[]},"padding":{"unit":"px","top":"0","right":"0","bottom":"70","left":"0","isLinked":false}},"elements":[{"id":"30b360f4","settings":{"_column_size":100,"background_color_stop":{"unit":"%","size":0,"sizes":[]},"background_color_b_stop":{"unit":"%","size":100,"sizes":[]},"background_gradient_angle":{"unit":"deg","size":180,"sizes":[]},"background_xpos":{"unit":"px","size":0,"sizes":[]},"background_xpos_tablet":{"unit":"px","size":0,"sizes":[]},"background_xpos_mobile":{"unit":"px","size":0,"sizes":[]},"background_ypos":{"unit":"px","size":0,"sizes":[]},"background_ypos_tablet":{"unit":"px","size":0,"sizes":[]},"background_ypos_mobile":{"unit":"px","size":0,"sizes":[]},"background_bg_width":{"unit":"%","size":100,"sizes":[]},"background_bg_width_tablet":{"unit":"px","size":"","sizes":[]},"background_bg_width_mobile":{"unit":"px","size":"","sizes":[]},"background_hover_color_stop":{"unit":"%","size":0,"sizes":[]},"background_hover_color_b_stop":{"unit":"%","size":100,"sizes":[]},"background_hover_gradient_angle":{"unit":"deg","size":180,"sizes":[]},"background_hover_xpos":{"unit":"px","size":0,"sizes":[]},"background_hover_xpos_tablet":{"unit":"px","size":0,"sizes":[]},"background_hover_xpos_mobile":{"unit":"px","size":0,"sizes":[]},"background_hover_ypos":{"unit":"px","size":0,"sizes":[]},"background_hover_ypos_tablet":{"unit":"px","size":0,"sizes":[]},"background_hover_ypos_mobile":{"unit":"px","size":0,"sizes":[]},"background_hover_bg_width":{"unit":"%","size":100,"sizes":[]},"background_hover_bg_width_tablet":{"unit":"px","size":"","sizes":[]},"background_hover_bg_width_mobile":{"unit":"px","size":"","sizes":[]},"background_hover_transition":{"unit":"px","size":0.3,"sizes":[]},"background_overlay_color_stop":{"unit":"%","size":0,"sizes":[]},"background_overlay_color_b_stop":{"unit":"%","size":100,"sizes":[]},"background_overlay_gradient_angle":{"unit":"deg","size":180,"sizes":[]},"background_overlay_xpos":{"unit":"px","size":0,"sizes":[]},"background_overlay_xpos_tablet":{"unit":"px","size":0,"sizes":[]},"background_overlay_xpos_mobile":{"unit":"px","size":0,"sizes":[]},"background_overlay_ypos":{"unit":"px","size":0,"sizes":[]},"background_overlay_ypos_tablet":{"unit":"px","size":0,"sizes":[]},"background_overlay_ypos_mobile":{"unit":"px","size":0,"sizes":[]},"background_overlay_bg_width":{"unit":"%","size":100,"sizes":[]},"background_overlay_bg_width_tablet":{"unit":"px","size":"","sizes":[]},"background_overlay_bg_width_mobile":{"unit":"px","size":"","sizes":[]},"background_overlay_opacity":{"unit":"px","size":0.5,"sizes":[]},"css_filters_blur":{"unit":"px","size":0,"sizes":[]},"css_filters_brightness":{"unit":"px","size":100,"sizes":[]},"css_filters_contrast":{"unit":"px","size":100,"sizes":[]},"css_filters_saturate":{"unit":"px","size":100,"sizes":[]},"css_filters_hue":{"unit":"px","size":0,"sizes":[]},"background_overlay_hover_color_stop":{"unit":"%","size":0,"sizes":[]},"background_overlay_hover_color_b_stop":{"unit":"%","size":100,"sizes":[]},"background_overlay_hover_gradient_angle":{"unit":"deg","size":180,"sizes":[]},"background_overlay_hover_xpos":{"unit":"px","size":0,"sizes":[]},"background_overlay_hover_xpos_tablet":{"unit":"px","size":0,"sizes":[]},"background_overlay_hover_xpos_mobile":{"unit":"px","size":0,"sizes":[]},"background_overlay_hover_ypos":{"unit":"px","size":0,"sizes":[]},"background_overlay_hover_ypos_tablet":{"unit":"px","size":0,"sizes":[]},"background_overlay_hover_ypos_mobile":{"unit":"px","size":0,"sizes":[]},"background_overlay_hover_bg_width":{"unit":"%","size":100,"sizes":[]},"background_overlay_hover_bg_width_tablet":{"unit":"px","size":"","sizes":[]},"background_overlay_hover_bg_width_mobile":{"unit":"px","size":"","sizes":[]},"background_overlay_hover_opacity":{"unit":"px","size":0.5,"sizes":[]},"css_filters_hover_blur":{"unit":"px","size":0,"sizes":[]},"css_filters_hover_brightness":{"unit":"px","size":100,"sizes":[]},"css_filters_hover_contrast":{"unit":"px","size":100,"sizes":[]},"css_filters_hover_saturate":{"unit":"px","size":100,"sizes":[]},"css_filters_hover_hue":{"unit":"px","size":0,"sizes":[]},"background_overlay_hover_transition":{"unit":"px","size":0.3,"sizes":[]},"border_hover_transition":{"unit":"px","size":0.3,"sizes":[]}},"elements":[{"id":"55ced6d0","settings":{"title":"New Blog Posts","align":"center","typography_typography":"custom","typography_font_family":"Poppins","typography_font_size":{"unit":"px","size":30,"sizes":[]},"typography_font_weight":"500","typography_font_size_tablet":{"unit":"px","size":"","sizes":[]},"typography_font_size_mobile":{"unit":"px","size":"","sizes":[]},"typography_line_height":{"unit":"em","size":"","sizes":[]},"typography_line_height_tablet":{"unit":"em","size":"","sizes":[]},"typography_line_height_mobile":{"unit":"em","size":"","sizes":[]},"typography_letter_spacing":{"unit":"px","size":"","sizes":[]},"typography_letter_spacing_tablet":{"unit":"px","size":"","sizes":[]},"typography_letter_spacing_mobile":{"unit":"px","size":"","sizes":[]},"_background_color_stop":{"unit":"%","size":0,"sizes":[]},"_background_color_b_stop":{"unit":"%","size":100,"sizes":[]},"_background_gradient_angle":{"unit":"deg","size":180,"sizes":[]},"_background_xpos":{"unit":"px","size":0,"sizes":[]},"_background_xpos_tablet":{"unit":"px","size":0,"sizes":[]},"_background_xpos_mobile":{"unit":"px","size":0,"sizes":[]},"_background_ypos":{"unit":"px","size":0,"sizes":[]},"_background_ypos_tablet":{"unit":"px","size":0,"sizes":[]},"_background_ypos_mobile":{"unit":"px","size":0,"sizes":[]},"_background_bg_width":{"unit":"%","size":100,"sizes":[]},"_background_bg_width_tablet":{"unit":"px","size":"","sizes":[]},"_background_bg_width_mobile":{"unit":"px","size":"","sizes":[]},"_background_hover_color_stop":{"unit":"%","size":0,"sizes":[]},"_background_hover_color_b_stop":{"unit":"%","size":100,"sizes":[]},"_background_hover_gradient_angle":{"unit":"deg","size":180,"sizes":[]},"_background_hover_xpos":{"unit":"px","size":0,"sizes":[]},"_background_hover_xpos_tablet":{"unit":"px","size":0,"sizes":[]},"_background_hover_xpos_mobile":{"unit":"px","size":0,"sizes":[]},"_background_hover_ypos":{"unit":"px","size":0,"sizes":[]},"_background_hover_ypos_tablet":{"unit":"px","size":0,"sizes":[]},"_background_hover_ypos_mobile":{"unit":"px","size":0,"sizes":[]},"_background_hover_bg_width":{"unit":"%","size":100,"sizes":[]},"_background_hover_bg_width_tablet":{"unit":"px","size":"","sizes":[]},"_background_hover_bg_width_mobile":{"unit":"px","size":"","sizes":[]},"_background_hover_transition":{"unit":"px","size":"","sizes":[]},"_border_hover_transition":{"unit":"px","size":"","sizes":[]},"_element_custom_width":{"unit":"px","size":"","sizes":[]},"_element_custom_width_tablet":{"unit":"px","size":"","sizes":[]},"_element_custom_width_mobile":{"unit":"px","size":"","sizes":[]},"_offset_x":{"unit":"px","size":"0","sizes":[]},"_offset_x_tablet":{"unit":"px","size":"","sizes":[]},"_offset_x_mobile":{"unit":"px","size":"","sizes":[]},"_offset_x_end":{"unit":"px","size":"0","sizes":[]},"_offset_x_end_tablet":{"unit":"px","size":"","sizes":[]},"_offset_x_end_mobile":{"unit":"px","size":"","sizes":[]},"_offset_y":{"unit":"px","size":"0","sizes":[]},"_offset_y_tablet":{"unit":"px","size":"","sizes":[]},"_offset_y_mobile":{"unit":"px","size":"","sizes":[]},"_offset_y_end":{"unit":"px","size":"0","sizes":[]},"_offset_y_end_tablet":{"unit":"px","size":"","sizes":[]},"_offset_y_end_mobile":{"unit":"px","size":"","sizes":[]}},"elements":[],"isInner":false,"widgetType":"heading","elType":"widget"},{"id":"679e48aa","settings":{"title":"Contrary to popular belief, Lorem Ipsum is not simply random <br\/>text. It has roots in a piece of classical","header_size":"p","align":"center","title_color":"#5a5a5a","typography_typography":"custom","typography_font_family":"Poppins","typography_font_weight":"400","typography_line_height":{"unit":"px","size":24,"sizes":[]},"typography_font_size":{"unit":"px","size":"","sizes":[]},"typography_font_size_tablet":{"unit":"px","size":"","sizes":[]},"typography_font_size_mobile":{"unit":"px","size":"","sizes":[]},"typography_line_height_tablet":{"unit":"em","size":"","sizes":[]},"typography_line_height_mobile":{"unit":"em","size":"","sizes":[]},"typography_letter_spacing":{"unit":"px","size":"","sizes":[]},"typography_letter_spacing_tablet":{"unit":"px","size":"","sizes":[]},"typography_letter_spacing_mobile":{"unit":"px","size":"","sizes":[]},"_background_color_stop":{"unit":"%","size":0,"sizes":[]},"_background_color_b_stop":{"unit":"%","size":100,"sizes":[]},"_background_gradient_angle":{"unit":"deg","size":180,"sizes":[]},"_background_xpos":{"unit":"px","size":0,"sizes":[]},"_background_xpos_tablet":{"unit":"px","size":0,"sizes":[]},"_background_xpos_mobile":{"unit":"px","size":0,"sizes":[]},"_background_ypos":{"unit":"px","size":0,"sizes":[]},"_background_ypos_tablet":{"unit":"px","size":0,"sizes":[]},"_background_ypos_mobile":{"unit":"px","size":0,"sizes":[]},"_background_bg_width":{"unit":"%","size":100,"sizes":[]},"_background_bg_width_tablet":{"unit":"px","size":"","sizes":[]},"_background_bg_width_mobile":{"unit":"px","size":"","sizes":[]},"_background_hover_color_stop":{"unit":"%","size":0,"sizes":[]},"_background_hover_color_b_stop":{"unit":"%","size":100,"sizes":[]},"_background_hover_gradient_angle":{"unit":"deg","size":180,"sizes":[]},"_background_hover_xpos":{"unit":"px","size":0,"sizes":[]},"_background_hover_xpos_tablet":{"unit":"px","size":0,"sizes":[]},"_background_hover_xpos_mobile":{"unit":"px","size":0,"sizes":[]},"_background_hover_ypos":{"unit":"px","size":0,"sizes":[]},"_background_hover_ypos_tablet":{"unit":"px","size":0,"sizes":[]},"_background_hover_ypos_mobile":{"unit":"px","size":0,"sizes":[]},"_background_hover_bg_width":{"unit":"%","size":100,"sizes":[]},"_background_hover_bg_width_tablet":{"unit":"px","size":"","sizes":[]},"_background_hover_bg_width_mobile":{"unit":"px","size":"","sizes":[]},"_background_hover_transition":{"unit":"px","size":"","sizes":[]},"_border_hover_transition":{"unit":"px","size":"","sizes":[]},"_element_custom_width":{"unit":"px","size":"","sizes":[]},"_element_custom_width_tablet":{"unit":"px","size":"","sizes":[]},"_element_custom_width_mobile":{"unit":"px","size":"","sizes":[]},"_offset_x":{"unit":"px","size":"0","sizes":[]},"_offset_x_tablet":{"unit":"px","size":"","sizes":[]},"_offset_x_mobile":{"unit":"px","size":"","sizes":[]},"_offset_x_end":{"unit":"px","size":"0","sizes":[]},"_offset_x_end_tablet":{"unit":"px","size":"","sizes":[]},"_offset_x_end_mobile":{"unit":"px","size":"","sizes":[]},"_offset_y":{"unit":"px","size":"0","sizes":[]},"_offset_y_tablet":{"unit":"px","size":"","sizes":[]},"_offset_y_mobile":{"unit":"px","size":"","sizes":[]},"_offset_y_end":{"unit":"px","size":"0","sizes":[]},"_offset_y_end_tablet":{"unit":"px","size":"","sizes":[]},"_offset_y_end_mobile":{"unit":"px","size":"","sizes":[]}},"elements":[],"isInner":false,"widgetType":"heading","elType":"widget"},{"id":"65c4969a","settings":{"content_len":19,"_margin":{"unit":"px","top":"40","right":"0","bottom":"0","left":"0","isLinked":false},"blog_title_typography_typography":"custom","blog_title_typography_font_family":"Poppins","blog_content_typography_typography":"custom","blog_content_typography_font_family":"Poppins","blog_content_typography_font_weight":"400","blog_meta_typography_typography":"custom","blog_meta_typography_font_family":"Poppins","blog_meta_typography_font_weight":"400"},"elements":[],"isInner":false,"widgetType":"parlo-latestblog-addons","elType":"widget"}],"isInner":false,"elType":"column"}],"isInner":false,"elType":"section"}]}